{"CityId":"58422785","CitySearchName":"R\u0113zekne","Streets":[{"Id":"38054834","CountryCode":"LV","Name":"Varo\u0146u iela","NameEN":"","NameDE":"","NameES":"","NameFR":"","NameIT":"","NameRU":""},{"Id":"38053984","CountryCode":"LV","Name":"B\u0113rzpils iela","NameEN":"","NameDE":"","NameES":"","NameFR":"","NameIT":"","NameRU":""},{"Id":"cdb8ad7b-657e-4673-b39d-c0c10a12b0c4","CountryCode":"LV","Name":"J. Ti\u0146anova iela","NameEN":null,"NameDE":null,"NameES":null,"NameFR":null,"NameIT":null,"NameRU":null},{"Id":"265716308","CountryCode":"LV","Name":"Tor\u0146a iela","NameEN":"","NameDE":"","NameES":"","NameFR":"","NameIT":"","NameRU":""},{"Id":"37997967","CountryCode":"LV","Name":"R\u016Bpn\u012Bcas iela","NameEN":"","NameDE":"","NameES":"","NameFR":"","NameIT":"","NameRU":""},{"Id":"38000320","CountryCode":"LV","Name":"Latgales iela","NameEN":"","NameDE":"","NameES":"","NameFR":"","NameIT":"","NameRU":""},{"Id":"35741724","CountryCode":"LV","Name":"Saules iela","NameEN":"","NameDE":"","NameES":"","NameFR":"","NameIT":"","NameRU":""},{"Id":"37999806","CountryCode":"LV","Name":"Liepu iela","NameEN":"","NameDE":"","NameES":"","NameFR":"","NameIT":"","NameRU":""},{"Id":"38613907","CountryCode":"LV","Name":"Krasta iela","NameEN":"Krasta Street","NameDE":"","NameES":"","NameFR":"","NameIT":"","NameRU":"\u0443\u043B\u0438\u0446\u0430 \u041A\u0440\u0430\u0441\u0442\u0430"},{"Id":"4b0ce15d-b469-4231-a89c-66a7dc05a54e","CountryCode":"LV","Name":"N. Ranc\u0101na iela","NameEN":null,"NameDE":null,"NameES":null,"NameFR":null,"NameIT":null,"NameRU":null},{"Id":"35741720","CountryCode":"LV","Name":"F. Varslav\u0101na iela","NameEN":"","NameDE":"","NameES":"","NameFR":"","NameIT":"","NameRU":""},{"Id":"38054000","CountryCode":"LV","Name":"Medi\u0137u iela","NameEN":"","NameDE":"","NameES":"","NameFR":"","NameIT":"","NameRU":""},{"Id":"38054585","CountryCode":"LV","Name":"Lakst\u012Bgalu iela","NameEN":"","NameDE":"","NameES":"","NameFR":"","NameIT":"","NameRU":""},{"Id":"38054002","CountryCode":"LV","Name":"Upes iela","NameEN":"","NameDE":"","NameES":"","NameFR":"","NameIT":"","NameRU":""},{"Id":"466157627","CountryCode":"LV","Name":"Spr\u016B\u017Eevas iela","NameEN":"","NameDE":"","NameES":"","NameFR":"","NameIT":"","NameRU":""},{"Id":"28219070","CountryCode":"LV","Name":"Zilupes iela","NameEN":"","NameDE":"","NameES":"","NameFR":"","NameIT":"","NameRU":""},{"Id":"35742268","CountryCode":"LV","Name":"Krimuldas iela","NameEN":"","NameDE":"","NameES":"","NameFR":"","NameIT":"","NameRU":""},{"Id":"55e97dd7-263d-4fa2-b5c2-9f629e01c42c","CountryCode":"LV","Name":"Kr. Barona iela","NameEN":null,"NameDE":null,"NameES":null,"NameFR":null,"NameIT":null,"NameRU":null},{"Id":"2d712cce-57dc-40bc-b53d-837cd64728b5","CountryCode":"LV","Name":"A. Up\u012B\u0161a iela","NameEN":null,"NameDE":null,"NameES":null,"NameFR":null,"NameIT":null,"NameRU":null},{"Id":"38054570","CountryCode":"LV","Name":"Jaunpleik\u0161\u0146u iela","NameEN":"","NameDE":"","NameES":"","NameFR":"","NameIT":"","NameRU":""},{"Id":"38054561","CountryCode":"LV","Name":"Pils iela","NameEN":"","NameDE":"","NameES":"","NameFR":"","NameIT":"","NameRU":""},{"Id":"520909364","CountryCode":"LV","Name":"Gravas iela","NameEN":"","NameDE":"","NameES":"","NameFR":"","NameIT":"","NameRU":""},{"Id":"7981306","CountryCode":"LV","Name":"R\u0113znas iela","NameEN":"","NameDE":"","NameES":"","NameFR":"","NameIT":"","NameRU":""},{"Id":"00a67a81-967a-41f8-b739-fe951669e7c0","CountryCode":"LV","Name":"F. Tras\u016Bna iela","NameEN":null,"NameDE":null,"NameES":null,"NameFR":null,"NameIT":null,"NameRU":null},{"Id":"38000315","CountryCode":"LV","Name":"Smil\u0161u iela","NameEN":"","NameDE":"","NameES":"","NameFR":"","NameIT":"","NameRU":""},{"Id":"38053979","CountryCode":"LV","Name":"Dzirnavu iela","NameEN":"","NameDE":"","NameES":"","NameFR":"","NameIT":"","NameRU":""},{"Id":"38054016","CountryCode":"LV","Name":"Stadiona iela","NameEN":"","NameDE":"","NameES":"","NameFR":"","NameIT":"","NameRU":""},{"Id":"37999808","CountryCode":"LV","Name":"Kuld\u012Bgas iela","NameEN":"","NameDE":"","NameES":"","NameFR":"","NameIT":"","NameRU":""},{"Id":"38054008","CountryCode":"LV","Name":"Stacijas iela","NameEN":"","NameDE":"","NameES":"","NameFR":"","NameIT":"","NameRU":""},{"Id":"41603777","CountryCode":"LV","Name":"R\u012Bgas iela","NameEN":"","NameDE":"","NameES":"","NameFR":"","NameIT":"","NameRU":""},{"Id":"22916790","CountryCode":"LV","Name":"Br\u012Bv\u012Bbas iela","NameEN":"","NameDE":"","NameES":"","NameFR":"","NameIT":"","NameRU":""},{"Id":"38074630","CountryCode":"LV","Name":"Bukmui\u017Eas iela","NameEN":"","NameDE":"","NameES":"","NameFR":"","NameIT":"","NameRU":""},{"Id":"35783944","CountryCode":"LV","Name":"Lub\u0101nas iela","NameEN":"","NameDE":"","NameES":"","NameFR":"","NameIT":"","NameRU":""},{"Id":"5b677b3e-9b25-4526-9dc8-5120800cb5ff","CountryCode":"LV","Name":"Taku iela","NameEN":null,"NameDE":null,"NameES":null,"NameFR":null,"NameIT":null,"NameRU":null},{"Id":"37999807","CountryCode":"LV","Name":"Kaunatas iela","NameEN":"","NameDE":"","NameES":"","NameFR":"","NameIT":"","NameRU":""},{"Id":"35741725","CountryCode":"LV","Name":"Daugavpils iela","NameEN":"","NameDE":"","NameES":"","NameFR":"","NameIT":"","NameRU":"\u0443\u043B\u0438\u0446\u0430 \u0414\u0430\u0443\u0433\u0430\u0432\u043F\u0438\u043B\u0441"},{"Id":"38000312","CountryCode":"LV","Name":"Jaunjelgavas iela","NameEN":"","NameDE":"","NameES":"","NameFR":"","NameIT":"","NameRU":""},{"Id":"0dfbfcaa-0fc6-4ab3-a4a8-41b60fbd6f22","CountryCode":"LV","Name":"\u0136ir\u0161u iela","NameEN":null,"NameDE":null,"NameES":null,"NameFR":null,"NameIT":null,"NameRU":null},{"Id":"35783937","CountryCode":"LV","Name":"Rai\u0146a iela","NameEN":"","NameDE":"","NameES":"","NameFR":"","NameIT":"","NameRU":""},{"Id":"38054584","CountryCode":"LV","Name":"Maz\u0101 iela","NameEN":"","NameDE":"","NameES":"","NameFR":"","NameIT":"","NameRU":""},{"Id":"35783934","CountryCode":"LV","Name":"Dzelzce\u013Cnieku iela","NameEN":"","NameDE":"","NameES":"","NameFR":"","NameIT":"","NameRU":""},{"Id":"df6a6ebb-616c-4c16-8226-10f4d60b0e15","CountryCode":"LV","Name":"Kr. Valdem\u0101ra iela","NameEN":null,"NameDE":null,"NameES":null,"NameFR":null,"NameIT":null,"NameRU":null},{"Id":"7982321","CountryCode":"LV","Name":"Atbr\u012Bvo\u0161anas aleja","NameEN":"","NameDE":"","NameES":"","NameFR":"","NameIT":"","NameRU":""},{"Id":"38054581","CountryCode":"LV","Name":"L\u012Bk\u0101 iela","NameEN":"","NameDE":"","NameES":"","NameFR":"","NameIT":"","NameRU":""},{"Id":"38054206","CountryCode":"LV","Name":"Vidus iela","NameEN":"","NameDE":"","NameES":"","NameFR":"","NameIT":"","NameRU":""},{"Id":"40122962","CountryCode":"LV","Name":"Vi\u013Cakas iela","NameEN":"","NameDE":"","NameES":"","NameFR":"","NameIT":"","NameRU":""},{"Id":"26626408","CountryCode":"LV","Name":"Ludzas iela","NameEN":"","NameDE":"","NameES":"","NameFR":"","NameIT":"","NameRU":""},{"Id":"38053982","CountryCode":"LV","Name":"Pulkve\u017Ea Brie\u017Ea iela","NameEN":"","NameDE":"","NameES":"","NameFR":"","NameIT":"","NameRU":"\u0443\u043B\u0438\u0446\u0430 \u041F\u0443\u043B\u043A\u0432\u0435\u0436\u0430 \u0411\u0440\u0438\u0435\u0436\u0430"},{"Id":"38000321","CountryCode":"LV","Name":"Jelgavas iela","NameEN":"","NameDE":"","NameES":"","NameFR":"","NameIT":"","NameRU":""},{"Id":"38000316","CountryCode":"LV","Name":"Miera iela","NameEN":"","NameDE":"","NameES":"","NameFR":"","NameIT":"","NameRU":""},{"Id":"38054221","CountryCode":"LV","Name":"Klus\u0101 iela","NameEN":"","NameDE":"","NameES":"","NameFR":"","NameIT":"","NameRU":""},{"Id":"38000317","CountryCode":"LV","Name":"Ro\u017Eu iela","NameEN":"","NameDE":"","NameES":"","NameFR":"","NameIT":"","NameRU":""},{"Id":"65577851","CountryCode":"LV","Name":"Vi\u013C\u0101nu iela","NameEN":"","NameDE":"","NameES":"","NameFR":"","NameIT":"","NameRU":""},{"Id":"38054572","CountryCode":"LV","Name":"Siguldas iela","NameEN":"","NameDE":"","NameES":"","NameFR":"","NameIT":"","NameRU":""},{"Id":"38000327","CountryCode":"LV","Name":"Kal\u0113ju iela","NameEN":"","NameDE":"","NameES":"","NameFR":"","NameIT":"","NameRU":"\u0443\u043B\u0438\u0446\u0430 \u041A\u0430\u043B\u0435\u044E"},{"Id":"ccdbb20e-ff4b-460c-9485-a72161c79397","CountryCode":"LV","Name":"V. Purv\u012B\u0161a iela","NameEN":null,"NameDE":null,"NameES":null,"NameFR":null,"NameIT":null,"NameRU":null},{"Id":"38054005","CountryCode":"LV","Name":"D\u0101rzu iela","NameEN":"","NameDE":"","NameES":"","NameFR":"","NameIT":"","NameRU":""},{"Id":"35741723","CountryCode":"LV","Name":"Robe\u017Eu iela","NameEN":"","NameDE":"","NameES":"","NameFR":"","NameIT":"","NameRU":""},{"Id":"38078910","CountryCode":"LV","Name":"Zvaig\u017E\u0146u iela","NameEN":"","NameDE":"","NameES":"","NameFR":"","NameIT":"","NameRU":""},{"Id":"507577911","CountryCode":"LV","Name":"Prie\u017Eu iela","NameEN":"","NameDE":"","NameES":"","NameFR":"","NameIT":"","NameRU":""},{"Id":"38054582","CountryCode":"LV","Name":"\u013Bermontova iela","NameEN":"","NameDE":"","NameES":"","NameFR":"","NameIT":"","NameRU":""},{"Id":"38000311","CountryCode":"LV","Name":"Gvardes iela","NameEN":"","NameDE":"","NameES":"","NameFR":"","NameIT":"","NameRU":""},{"Id":"37999812","CountryCode":"LV","Name":"Jaunprojekta iela","NameEN":"","NameDE":"","NameES":"","NameFR":"","NameIT":"","NameRU":""},{"Id":"38054211","CountryCode":"LV","Name":"Ausek\u013Ca iela","NameEN":"","NameDE":"","NameES":"","NameFR":"","NameIT":"","NameRU":""},{"Id":"38054010","CountryCode":"LV","Name":"Ventspils iela","NameEN":"","NameDE":"","NameES":"","NameFR":"","NameIT":"","NameRU":""},{"Id":"38056782","CountryCode":"LV","Name":"Me\u017Ea iela","NameEN":"","NameDE":"","NameES":"","NameFR":"","NameIT":"","NameRU":""},{"Id":"35730869","CountryCode":"LV","Name":"18. novembra iela","NameEN":"","NameDE":"","NameES":"","NameFR":"","NameIT":"","NameRU":""},{"Id":"332128061","CountryCode":"LV","Name":"Str\u0101dnieku \u0161\u0137\u0113rsiela","NameEN":"","NameDE":"","NameES":"","NameFR":"","NameIT":"","NameRU":""},{"Id":"991769240","CountryCode":"LV","Name":"P\u013Cavu iela","NameEN":"","NameDE":"","NameES":"","NameFR":"","NameIT":"","NameRU":""},{"Id":"38054579","CountryCode":"LV","Name":"K\u016Bdras iela","NameEN":"","NameDE":"","NameES":"","NameFR":"","NameIT":"","NameRU":""},{"Id":"38054001","CountryCode":"LV","Name":"Zemnieku iela","NameEN":"","NameDE":"","NameES":"","NameFR":"","NameIT":"","NameRU":""},{"Id":"37997966","CountryCode":"LV","Name":"Blauma\u0146a iela","NameEN":"","NameDE":"","NameES":"","NameFR":"","NameIT":"","NameRU":""},{"Id":"38805772","CountryCode":"LV","Name":"Celtnieku iela","NameEN":"","NameDE":"","NameES":"","NameFR":"","NameIT":"","NameRU":""},{"Id":"38054205","CountryCode":"LV","Name":"Parka iela","NameEN":"","NameDE":"","NameES":"","NameFR":"","NameIT":"","NameRU":""},{"Id":"265716307","CountryCode":"LV","Name":"Lokomot\u012Bvju iela","NameEN":"","NameDE":"","NameES":"","NameFR":"","NameIT":"","NameRU":""},{"Id":"1120450272","CountryCode":"LV","Name":"\u010Ca\u010Du iela","NameEN":"","NameDE":"","NameES":"","NameFR":"","NameIT":"","NameRU":""},{"Id":"367433738","CountryCode":"LV","Name":"Jupatovkas iela","NameEN":"","NameDE":"","NameES":"","NameFR":"","NameIT":"","NameRU":""},{"Id":"367436576","CountryCode":"LV","Name":"\u0100be\u013Cu iela","NameEN":"","NameDE":"","NameES":"","NameFR":"","NameIT":"","NameRU":""},{"Id":"38054214","CountryCode":"LV","Name":"Vipingas iela","NameEN":"","NameDE":"","NameES":"","NameFR":"","NameIT":"","NameRU":""},{"Id":"508211742","CountryCode":"LV","Name":"Krustpils iela","NameEN":"","NameDE":"","NameES":"","NameFR":"","NameIT":"","NameRU":""},{"Id":"38054565","CountryCode":"LV","Name":"Turaidas iela","NameEN":"","NameDE":"","NameES":"","NameFR":"","NameIT":"","NameRU":""},{"Id":"38054557","CountryCode":"LV","Name":"Koku iela","NameEN":"","NameDE":"","NameES":"","NameFR":"","NameIT":"","NameRU":""},{"Id":"38054562","CountryCode":"LV","Name":"Valmieras iela","NameEN":"","NameDE":"","NameES":"","NameFR":"","NameIT":"","NameRU":""},{"Id":"38054563","CountryCode":"LV","Name":"Al\u016Bksnes iela","NameEN":"","NameDE":"","NameES":"","NameFR":"","NameIT":"","NameRU":""},{"Id":"508211744","CountryCode":"LV","Name":"An\u010Dup\u0101nu iela","NameEN":"","NameDE":"","NameES":"","NameFR":"","NameIT":"","NameRU":""},{"Id":"aef28d29-7709-44dd-9cc8-a272c526bc16","CountryCode":"LV","Name":"V. Seiles iela","NameEN":null,"NameDE":null,"NameES":null,"NameFR":null,"NameIT":null,"NameRU":null},{"Id":"3c5c3be1-6335-4c3b-b049-ab9e74137423","CountryCode":"LV","Name":"Ka\u013C\u0137u iela","NameEN":null,"NameDE":null,"NameES":null,"NameFR":null,"NameIT":null,"NameRU":null},{"Id":"38054003","CountryCode":"LV","Name":"Jaunupes iela","NameEN":"","NameDE":"","NameES":"","NameFR":"","NameIT":"","NameRU":""},{"Id":"38054831","CountryCode":"LV","Name":"Ezera iela","NameEN":"","NameDE":"","NameES":"","NameFR":"","NameIT":"","NameRU":""},{"Id":"38054580","CountryCode":"LV","Name":"Lauku iela","NameEN":"","NameDE":"","NameES":"","NameFR":"","NameIT":"","NameRU":""},{"Id":"38000328","CountryCode":"LV","Name":"Kr\u0101slavas iela","NameEN":"","NameDE":"","NameES":"","NameFR":"","NameIT":"","NameRU":""},{"Id":"339538893","CountryCode":"LV","Name":"P\u016Bpolu iela","NameEN":"","NameDE":"","NameES":"","NameFR":"","NameIT":"","NameRU":""},{"Id":"35783936","CountryCode":"LV","Name":"Br\u0101\u013Cu Skrindu iela","NameEN":"","NameDE":"","NameES":"","NameFR":"","NameIT":"","NameRU":""},{"Id":"38054215","CountryCode":"LV","Name":"Ozolu iela","NameEN":"","NameDE":"","NameES":"","NameFR":"","NameIT":"","NameRU":""},{"Id":"38054586","CountryCode":"LV","Name":"Kalna iela","NameEN":"","NameDE":"","NameES":"","NameFR":"","NameIT":"","NameRU":""},{"Id":"755698968","CountryCode":"LV","Name":"Lapu iela","NameEN":"","NameDE":"","NameES":"","NameFR":"","NameIT":"","NameRU":""},{"Id":"38053980","CountryCode":"LV","Name":"Bazn\u012Bcas iela","NameEN":"","NameDE":"","NameES":"","NameFR":"","NameIT":"","NameRU":""},{"Id":"38054220","CountryCode":"LV","Name":"F. Kempa iela","NameEN":"","NameDE":"","NameES":"","NameFR":"","NameIT":"","NameRU":""},{"Id":"4a518fc0-d9c0-4a04-8054-d35e438e1863","CountryCode":"LV","Name":"S. Put\u0101na iela","NameEN":null,"NameDE":null,"NameES":null,"NameFR":null,"NameIT":null,"NameRU":null},{"Id":"38054017","CountryCode":"LV","Name":"Slimn\u012Bcas iela","NameEN":"","NameDE":"","NameES":"","NameFR":"","NameIT":"","NameRU":""},{"Id":"691945970","CountryCode":"LV","Name":"Purva iela","NameEN":"","NameDE":"","NameES":"","NameFR":"","NameIT":"","NameRU":""},{"Id":"1000316587","CountryCode":"LV","Name":"Gr\u0101vju iela","NameEN":"","NameDE":"","NameES":"","NameFR":"","NameIT":"","NameRU":""},{"Id":"38807133","CountryCode":"LV","Name":"Noliktavu iela","NameEN":"","NameDE":"","NameES":"","NameFR":"","NameIT":"","NameRU":""},{"Id":"38000313","CountryCode":"LV","Name":"Ziedu iela","NameEN":"","NameDE":"","NameES":"","NameFR":"","NameIT":"","NameRU":""},{"Id":"35741718","CountryCode":"LV","Name":"Zavoloko iela","NameEN":"","NameDE":"","NameES":"","NameFR":"","NameIT":"","NameRU":""},{"Id":"b31c03b7-7648-46ff-852e-4e50a6fd8876","CountryCode":"LV","Name":"A. Pumpura iela","NameEN":null,"NameDE":null,"NameES":null,"NameFR":null,"NameIT":null,"NameRU":null},{"Id":"38054575","CountryCode":"LV","Name":"Str\u0113lnieku iela","NameEN":"","NameDE":"","NameES":"","NameFR":"","NameIT":"","NameRU":""},{"Id":"35783940","CountryCode":"LV","Name":"Skolas iela","NameEN":"","NameDE":"","NameES":"","NameFR":"","NameIT":"","NameRU":""},{"Id":"38613908","CountryCode":"LV","Name":"Galdnieku iela","NameEN":"","NameDE":"","NameES":"","NameFR":"","NameIT":"","NameRU":""},{"Id":"38054228","CountryCode":"LV","Name":"Keramikas iela","NameEN":"","NameDE":"","NameES":"","NameFR":"","NameIT":"","NameRU":""},{"Id":"38054583","CountryCode":"LV","Name":"N\u0101kotnes iela","NameEN":"","NameDE":"","NameES":"","NameFR":"","NameIT":"","NameRU":""},{"Id":"38807134","CountryCode":"LV","Name":"Maskavas iela","NameEN":"","NameDE":"","NameES":"","NameFR":"","NameIT":"","NameRU":""},{"Id":"37999809","CountryCode":"LV","Name":"Bauskas iela","NameEN":"","NameDE":"","NameES":"","NameFR":"","NameIT":"","NameRU":""},{"Id":"c8783f15-8d9d-4540-9382-c9ae21ef67d7","CountryCode":"LV","Name":"Akme\u0146u iela","NameEN":null,"NameDE":null,"NameES":null,"NameFR":null,"NameIT":null,"NameRU":null},{"Id":"38054015","CountryCode":"LV","Name":"Za\u013C\u0101 iela","NameEN":"","NameDE":"","NameES":"","NameFR":"","NameIT":"","NameRU":""},{"Id":"40122964","CountryCode":"LV","Name":"Komun\u0101l\u0101 iela","NameEN":"","NameDE":"","NameES":"","NameFR":"","NameIT":"","NameRU":""},{"Id":"546b68ac-5f93-4e9b-8a87-6d0b43a3d0e6","CountryCode":"LV","Name":"Austrumu iela","NameEN":null,"NameDE":null,"NameES":null,"NameFR":null,"NameIT":null,"NameRU":null},{"Id":"38054213","CountryCode":"LV","Name":"Eg\u013Cu iela","NameEN":"","NameDE":"","NameES":"","NameFR":"","NameIT":"","NameRU":""},{"Id":"35783945","CountryCode":"LV","Name":"Kosmonautu iela","NameEN":"","NameDE":"","NameES":"","NameFR":"","NameIT":"","NameRU":""},{"Id":"38054573","CountryCode":"LV","Name":"Zvirbu\u013Cu iela","NameEN":"","NameDE":"","NameES":"","NameFR":"","NameIT":"","NameRU":""},{"Id":"37997969","CountryCode":"LV","Name":"Met\u0101listu iela","NameEN":"","NameDE":"","NameES":"","NameFR":"","NameIT":"","NameRU":""},{"Id":"37997970","CountryCode":"LV","Name":"Atmodas iela","NameEN":"","NameDE":"","NameES":"","NameFR":"","NameIT":"","NameRU":""},{"Id":"292839078","CountryCode":"LV","Name":"Liep\u0101jas iela","NameEN":"","NameDE":"","NameES":"","NameFR":"","NameIT":"","NameRU":""},{"Id":"38054012","CountryCode":"LV","Name":"8. marta iela","NameEN":"","NameDE":"","NameES":"","NameFR":"","NameIT":"","NameRU":""},{"Id":"38054577","CountryCode":"LV","Name":"Kr\u0101sot\u0101ju iela","NameEN":"","NameDE":"","NameES":"","NameFR":"","NameIT":"","NameRU":""},{"Id":"38054554","CountryCode":"LV","Name":"Kooperat\u012Bva \u0161\u0137\u0113rsiela","NameEN":"","NameDE":"","NameES":"","NameFR":"","NameIT":"","NameRU":""},{"Id":"40123200","CountryCode":"LV","Name":"B\u0113rzu iela","NameEN":"","NameDE":"","NameES":"","NameFR":"","NameIT":"","NameRU":""},{"Id":"e24b37ac-2bf8-4c43-a92a-5ef3f2922648","CountryCode":"LV","Name":"Si\u0146icina iela","NameEN":null,"NameDE":null,"NameES":null,"NameFR":null,"NameIT":null,"NameRU":null},{"Id":"292839076","CountryCode":"LV","Name":"Izra\u0113las iela","NameEN":"","NameDE":"","NameES":"","NameFR":"","NameIT":"","NameRU":""},{"Id":"38055343","CountryCode":"LV","Name":"Zieme\u013Cu iela","NameEN":"","NameDE":"","NameES":"","NameFR":"","NameIT":"","NameRU":""},{"Id":"367431984","CountryCode":"LV","Name":"Dagdas iela","NameEN":"","NameDE":"","NameES":"","NameFR":"","NameIT":"","NameRU":""},{"Id":"38054568","CountryCode":"LV","Name":"Dzintaru iela","NameEN":"","NameDE":"","NameES":"","NameFR":"","NameIT":"","NameRU":""},{"Id":"65690d3b-5114-45d6-b42e-519f1a3aefab","CountryCode":"LV","Name":"C\u0113su iela","NameEN":null,"NameDE":null,"NameES":null,"NameFR":null,"NameIT":null,"NameRU":null},{"Id":"0f18a33f-98d8-4e5c-a32e-2a6302e1c28f","CountryCode":"LV","Name":"\u012As\u0101 iela","NameEN":null,"NameDE":null,"NameES":null,"NameFR":null,"NameIT":null,"NameRU":null},{"Id":"abc64130-5515-4db5-8413-74c9b3d89982","CountryCode":"LV","Name":"Lokomot\u012Bvju \u0161\u0137\u0113rsiela","NameEN":null,"NameDE":null,"NameES":null,"NameFR":null,"NameIT":null,"NameRU":null},{"Id":"01f1d9e6-3c94-4c85-bc9b-423f71437be1","CountryCode":"LV","Name":"Pirts iela","NameEN":null,"NameDE":null,"NameES":null,"NameFR":null,"NameIT":null,"NameRU":null},{"Id":"3bb2d245-6f9a-4f12-976e-f9ea30a2e2a0","CountryCode":"LV","Name":"Eksporta iela","NameEN":null,"NameDE":null,"NameES":null,"NameFR":null,"NameIT":null,"NameRU":null}]}