{"CityId":"253543591","CitySearchName":"Che\u0142m","Streets":[{"Id":"33024686","CountryCode":"PL","Name":"Kolejowa","NameEN":"","NameDE":"","NameES":"","NameFR":"","NameIT":"","NameRU":""},{"Id":"51163173","CountryCode":"PL","Name":"Lwowska","NameEN":"","NameDE":"","NameES":"","NameFR":"","NameIT":"","NameRU":""},{"Id":"25450474","CountryCode":"PL","Name":"Aleja Armii Krajowej","NameEN":"","NameDE":"","NameES":"","NameFR":"","NameIT":"","NameRU":""},{"Id":"33020717","CountryCode":"PL","Name":"Poleg\u0142ych","NameEN":"","NameDE":"","NameES":"","NameFR":"","NameIT":"","NameRU":""},{"Id":"72431858","CountryCode":"PL","Name":"Plac Niepodleg\u0142o\u015Bci","NameEN":"","NameDE":"","NameES":"","NameFR":"","NameIT":"","NameRU":""},{"Id":"33029250","CountryCode":"PL","Name":"Aleja \u017Bo\u0142nierzy I Armii Wojska Polskiego","NameEN":"","NameDE":"","NameES":"","NameFR":"","NameIT":"","NameRU":""},{"Id":"33016760","CountryCode":"PL","Name":"Lubelska","NameEN":"","NameDE":"","NameES":"","NameFR":"","NameIT":"","NameRU":""},{"Id":"309141097","CountryCode":"PL","Name":"Partyzant\u00F3w","NameEN":"","NameDE":"","NameES":"","NameFR":"","NameIT":"","NameRU":""},{"Id":"33027160","CountryCode":"PL","Name":"Ogrodowa","NameEN":"","NameDE":"","NameES":"","NameFR":"","NameIT":"","NameRU":""},{"Id":"86321351","CountryCode":"PL","Name":"Nowowiejska","NameEN":"","NameDE":"","NameES":"","NameFR":"","NameIT":"","NameRU":""},{"Id":"33034659","CountryCode":"PL","Name":"Jagiello\u0144ska","NameEN":"","NameDE":"","NameES":"","NameFR":"","NameIT":"","NameRU":""},{"Id":"33018989","CountryCode":"PL","Name":"Lipowa","NameEN":"","NameDE":"","NameES":"","NameFR":"","NameIT":"","NameRU":""},{"Id":"33013960","CountryCode":"PL","Name":"Polna","NameEN":"","NameDE":"","NameES":"","NameFR":"","NameIT":"","NameRU":""},{"Id":"23735080","CountryCode":"PL","Name":"Le\u015Bna","NameEN":"","NameDE":"","NameES":"","NameFR":"","NameIT":"","NameRU":""},{"Id":"86830659","CountryCode":"PL","Name":"Stawowa","NameEN":"","NameDE":"","NameES":"","NameFR":"","NameIT":"","NameRU":""},{"Id":"224918722","CountryCode":"PL","Name":"Ksi\u0119dza Franciszka Rogaczewskiego","NameEN":"","NameDE":"","NameES":"","NameFR":"","NameIT":"","NameRU":""},{"Id":"177218551","CountryCode":"PL","Name":"Biskupia","NameEN":"","NameDE":"","NameES":"","NameFR":"","NameIT":"","NameRU":""},{"Id":"27476716","CountryCode":"PL","Name":"Pohulanka","NameEN":"","NameDE":"","NameES":"","NameFR":"","NameIT":"","NameRU":""},{"Id":"27476753","CountryCode":"PL","Name":"Lubuska","NameEN":"","NameDE":"","NameES":"","NameFR":"","NameIT":"","NameRU":""},{"Id":"60103278","CountryCode":"PL","Name":"Stoczniowc\u00F3w","NameEN":"","NameDE":"","NameES":"","NameFR":"","NameIT":"","NameRU":""},{"Id":"177218560","CountryCode":"PL","Name":"Zielonog\u00F3rska","NameEN":"","NameDE":"","NameES":"","NameFR":"","NameIT":"","NameRU":""},{"Id":"27476592","CountryCode":"PL","Name":"Doker\u00F3w","NameEN":"","NameDE":"","NameES":"","NameFR":"","NameIT":"","NameRU":""},{"Id":"177218564","CountryCode":"PL","Name":"Kolonia Post\u0119p","NameEN":"","NameDE":"","NameES":"","NameFR":"","NameIT":"","NameRU":""},{"Id":"104979425","CountryCode":"PL","Name":"Kolonia Przysz\u0142o\u015B\u0107","NameEN":"","NameDE":"","NameES":"","NameFR":"","NameIT":"","NameRU":""},{"Id":"176021507","CountryCode":"PL","Name":"\u0141u\u017Cycka","NameEN":"","NameDE":"","NameES":"","NameFR":"","NameIT":"","NameRU":""},{"Id":"27477600","CountryCode":"PL","Name":"Stanis\u0142awa Worcella","NameEN":"","NameDE":"","NameES":"","NameFR":"","NameIT":"","NameRU":""},{"Id":"177224126","CountryCode":"PL","Name":"Bitwy Pod Lenino","NameEN":"","NameDE":"Hipperstra\u00DFe","NameES":"","NameFR":"","NameIT":"","NameRU":""},{"Id":"177224128","CountryCode":"PL","Name":"Lotnik\u00F3w Polskich","NameEN":"","NameDE":"","NameES":"","NameFR":"","NameIT":"","NameRU":""},{"Id":"33017414","CountryCode":"PL","Name":"Reformacka","NameEN":"","NameDE":"","NameES":"","NameFR":"","NameIT":"","NameRU":""},{"Id":"177218552","CountryCode":"PL","Name":"Ludwika Hirszfelda","NameEN":"","NameDE":"","NameES":"","NameFR":"","NameIT":"","NameRU":""},{"Id":"27477680","CountryCode":"PL","Name":"Jana Styp-Rekowskiego","NameEN":"","NameDE":"","NameES":"","NameFR":"","NameIT":"","NameRU":""},{"Id":"69416704","CountryCode":"PL","Name":"Biskupa Andrzeja Wronki","NameEN":"","NameDE":"","NameES":"","NameFR":"","NameIT":"","NameRU":""},{"Id":"104999524","CountryCode":"PL","Name":"Ludwika Rydygiera","NameEN":"","NameDE":"","NameES":"","NameFR":"","NameIT":"","NameRU":""},{"Id":"27476636","CountryCode":"PL","Name":"Odrza\u0144ska","NameEN":"","NameDE":"","NameES":"","NameFR":"","NameIT":"","NameRU":""},{"Id":"27476726","CountryCode":"PL","Name":"W\u0142adys\u0142awa Biega\u0144skiego","NameEN":"","NameDE":"","NameES":"","NameFR":"","NameIT":"","NameRU":""},{"Id":"27476453","CountryCode":"PL","Name":"Tytusa Cha\u0142ubi\u0144skiego","NameEN":"","NameDE":"","NameES":"","NameFR":"","NameIT":"","NameRU":""},{"Id":"60235398","CountryCode":"PL","Name":"Witolda Grabowskiego","NameEN":"","NameDE":"","NameES":"","NameFR":"","NameIT":"","NameRU":""},{"Id":"177224113","CountryCode":"PL","Name":"Edmunda Biernackiego","NameEN":"","NameDE":"","NameES":"","NameFR":"","NameIT":"","NameRU":""},{"Id":"60892098","CountryCode":"PL","Name":"Cienista","NameEN":"","NameDE":"","NameES":"","NameFR":"","NameIT":"","NameRU":""},{"Id":"60892128","CountryCode":"PL","Name":"Lubomira Szopi\u0144skiego","NameEN":"","NameDE":"","NameES":"","NameFR":"","NameIT":"","NameRU":""},{"Id":"27477891","CountryCode":"PL","Name":"Henryka Hubertusa Jab\u0142o\u0144skiego","NameEN":"","NameDE":"","NameES":"","NameFR":"","NameIT":"","NameRU":""},{"Id":"27477612","CountryCode":"PL","Name":"Zamiejska","NameEN":"","NameDE":"","NameES":"","NameFR":"","NameIT":"","NameRU":""},{"Id":"27478170","CountryCode":"PL","Name":"Antoniego Suchanka","NameEN":"","NameDE":"","NameES":"","NameFR":"","NameIT":"","NameRU":""},{"Id":"27475537","CountryCode":"PL","Name":"Stanis\u0142awa Hebanowskiego","NameEN":"","NameDE":"","NameES":"","NameFR":"","NameIT":"","NameRU":""},{"Id":"27476891","CountryCode":"PL","Name":"Marcina Dragana","NameEN":"","NameDE":"","NameES":"","NameFR":"","NameIT":"","NameRU":""},{"Id":"27476542","CountryCode":"PL","Name":"Wincentego Witosa","NameEN":"","NameDE":"","NameES":"","NameFR":"","NameIT":"","NameRU":""},{"Id":"27478263","CountryCode":"PL","Name":"Profesora Romualda Cebertowicza","NameEN":"","NameDE":"","NameES":"","NameFR":"","NameIT":"","NameRU":""},{"Id":"27476848","CountryCode":"PL","Name":"W\u0142adys\u0142awa Cieszy\u0144skiego","NameEN":"","NameDE":"","NameES":"","NameFR":"","NameIT":"","NameRU":""},{"Id":"27475533","CountryCode":"PL","Name":"Profesora Kazimierza Kopeckiego","NameEN":"","NameDE":"","NameES":"","NameFR":"","NameIT":"","NameRU":""},{"Id":"27475477","CountryCode":"PL","Name":"Profesora J\u00F3zefa Wi\u0119ckowskiego","NameEN":"","NameDE":"","NameES":"","NameFR":"","NameIT":"","NameRU":""},{"Id":"27475857","CountryCode":"PL","Name":"Profesora Romana Lipowicza","NameEN":"","NameDE":"","NameES":"","NameFR":"","NameIT":"","NameRU":""},{"Id":"105608544","CountryCode":"PL","Name":"Damazego Tilgnera","NameEN":"","NameDE":"","NameES":"","NameFR":"","NameIT":"","NameRU":""},{"Id":"27476799","CountryCode":"PL","Name":"Antoniego Madali\u0144skiego","NameEN":"","NameDE":"","NameES":"","NameFR":"","NameIT":"","NameRU":""},{"Id":"123180674","CountryCode":"PL","Name":"Nieborowska","NameEN":"","NameDE":"","NameES":"","NameFR":"","NameIT":"","NameRU":""},{"Id":"151591039","CountryCode":"PL","Name":"Wawelska","NameEN":"","NameDE":"","NameES":"","NameFR":"","NameIT":"","NameRU":""},{"Id":"33014507","CountryCode":"PL","Name":"D\u0105br\u00F3wki","NameEN":"","NameDE":"","NameES":"","NameFR":"","NameIT":"","NameRU":""},{"Id":"75391391","CountryCode":"PL","Name":"Kr\u00F3lowej Jadwigi","NameEN":"","NameDE":"","NameES":"","NameFR":"","NameIT":"","NameRU":""},{"Id":"184762516","CountryCode":"PL","Name":"Marii Ludwiki","NameEN":"","NameDE":"","NameES":"","NameFR":"","NameIT":"","NameRU":""},{"Id":"27478043","CountryCode":"PL","Name":"Anny Jagiellonki","NameEN":"","NameDE":"","NameES":"","NameFR":"","NameIT":"","NameRU":""},{"Id":"27478280","CountryCode":"PL","Name":"Bernarda Milskiego","NameEN":"","NameDE":"","NameES":"","NameFR":"","NameIT":"","NameRU":""},{"Id":"105589239","CountryCode":"PL","Name":"Ptasia","NameEN":"","NameDE":"","NameES":"","NameFR":"","NameIT":"","NameRU":""},{"Id":"131492221","CountryCode":"PL","Name":"Rogali\u0144ska","NameEN":"","NameDE":"","NameES":"","NameFR":"","NameIT":"","NameRU":""},{"Id":"226141172","CountryCode":"PL","Name":"\u0141a\u0144cucka","NameEN":"","NameDE":"","NameES":"","NameFR":"","NameIT":"","NameRU":""},{"Id":"151877403","CountryCode":"PL","Name":"Wilanowska","NameEN":"","NameDE":"","NameES":"","NameFR":"","NameIT":"","NameRU":""},{"Id":"131492217","CountryCode":"PL","Name":"Profesora Stanis\u0142awa Szpora","NameEN":"","NameDE":"","NameES":"","NameFR":"","NameIT":"","NameRU":""},{"Id":"33025471","CountryCode":"PL","Name":"Powsta\u0144c\u00F3w Warszawy","NameEN":"","NameDE":"","NameES":"","NameFR":"","NameIT":"","NameRU":""},{"Id":"27476459","CountryCode":"PL","Name":"\u015Awi\u0119tokrzyska","NameEN":"","NameDE":"","NameES":"","NameFR":"","NameIT":"","NameRU":""},{"Id":"187102665","CountryCode":"PL","Name":"Kr\u00F3lowej Bony","NameEN":"","NameDE":"","NameES":"","NameFR":"","NameIT":"","NameRU":""},{"Id":"23708488","CountryCode":"PL","Name":"Toszecka","NameEN":"","NameDE":"","NameES":"","NameFR":"","NameIT":"","NameRU":""},{"Id":"97098156","CountryCode":"PL","Name":"Poniszowicka","NameEN":"","NameDE":"","NameES":"","NameFR":"","NameIT":"","NameRU":""},{"Id":"33031912","CountryCode":"PL","Name":"Wo\u0142y\u0144ska","NameEN":"","NameDE":"","NameES":"","NameFR":"","NameIT":"","NameRU":""},{"Id":"33025324","CountryCode":"PL","Name":"Graniczna","NameEN":"","NameDE":"","NameES":"","NameFR":"","NameIT":"","NameRU":""},{"Id":"33030999","CountryCode":"PL","Name":"11 Listopada","NameEN":"","NameDE":"","NameES":"","NameFR":"","NameIT":"","NameRU":""},{"Id":"23719107","CountryCode":"PL","Name":"Gliwicka","NameEN":"","NameDE":"","NameES":"","NameFR":"","NameIT":"","NameRU":""},{"Id":"86113266","CountryCode":"PL","Name":"S\u0142upska","NameEN":"","NameDE":"","NameES":"","NameFR":"","NameIT":"","NameRU":""},{"Id":"33013266","CountryCode":"PL","Name":"Stra\u017Cacka","NameEN":"","NameDE":"","NameES":"","NameFR":"","NameIT":"","NameRU":""},{"Id":"32394074","CountryCode":"PL","Name":"Parkowa","NameEN":"","NameDE":"","NameES":"","NameFR":"","NameIT":"","NameRU":""},{"Id":"150190730","CountryCode":"PL","Name":"Cicha","NameEN":"","NameDE":"","NameES":"","NameFR":"","NameIT":"","NameRU":""},{"Id":"33027196","CountryCode":"PL","Name":"Sportowa","NameEN":"","NameDE":"","NameES":"","NameFR":"","NameIT":"","NameRU":""},{"Id":"23708655","CountryCode":"PL","Name":"Strzelecka","NameEN":"","NameDE":"","NameES":"","NameFR":"","NameIT":"","NameRU":""},{"Id":"33030631","CountryCode":"PL","Name":"S\u0142oneczna","NameEN":"","NameDE":"","NameES":"","NameFR":"","NameIT":"","NameRU":""},{"Id":"174883763","CountryCode":"PL","Name":"Starostrzelecka","NameEN":"","NameDE":"","NameES":"","NameFR":"","NameIT":"","NameRU":""},{"Id":"204844909","CountryCode":"PL","Name":"Plac Zamkowy","NameEN":"","NameDE":"","NameES":"","NameFR":"","NameIT":"","NameRU":""},{"Id":"23708656","CountryCode":"PL","Name":"Szkolna","NameEN":"","NameDE":"","NameES":"","NameFR":"","NameIT":"","NameRU":""},{"Id":"23708852","CountryCode":"PL","Name":"Plac 1 Maja","NameEN":"","NameDE":"","NameES":"","NameFR":"","NameIT":"","NameRU":""},{"Id":"23708836","CountryCode":"PL","Name":"Romualda Traugutta","NameEN":"","NameDE":"","NameES":"","NameFR":"","NameIT":"","NameRU":""},{"Id":"23708857","CountryCode":"PL","Name":"Konstantego Damrota","NameEN":"","NameDE":"","NameES":"","NameFR":"","NameIT":"","NameRU":""},{"Id":"174883762","CountryCode":"PL","Name":"Piotra Skargi","NameEN":"","NameDE":"","NameES":"","NameFR":"","NameIT":"","NameRU":""},{"Id":"174884106","CountryCode":"PL","Name":"Ko\u015Bcielna","NameEN":"","NameDE":"","NameES":"","NameFR":"","NameIT":"","NameRU":""},{"Id":"33027033","CountryCode":"PL","Name":"G\u00F3rna","NameEN":"","NameDE":"","NameES":"","NameFR":"","NameIT":"","NameRU":""},{"Id":"26088417","CountryCode":"PL","Name":"Pi\u0119kna","NameEN":"","NameDE":"","NameES":"","NameFR":"","NameIT":"","NameRU":""},{"Id":"33014273","CountryCode":"PL","Name":"Zachodnia","NameEN":"","NameDE":"","NameES":"","NameFR":"","NameIT":"","NameRU":""},{"Id":"33019238","CountryCode":"PL","Name":"Henryka Sienkiewicza","NameEN":"","NameDE":"","NameES":"","NameFR":"","NameIT":"","NameRU":""},{"Id":"33025128","CountryCode":"PL","Name":"Szpitalna","NameEN":"","NameDE":"","NameES":"","NameFR":"","NameIT":"","NameRU":""},{"Id":"86219919","CountryCode":"PL","Name":"Hetmana Stefana Czarnieckiego","NameEN":"","NameDE":"","NameES":"","NameFR":"","NameIT":"","NameRU":""},{"Id":"33015625","CountryCode":"PL","Name":"Miko\u0142aja Kopernika","NameEN":"","NameDE":"","NameES":"","NameFR":"","NameIT":"","NameRU":""},{"Id":"33015113","CountryCode":"PL","Name":"Wolno\u015Bci","NameEN":"","NameDE":"","NameES":"","NameFR":"","NameIT":"","NameRU":""},{"Id":"33035273","CountryCode":"PL","Name":"Ob\u0142o\u0144ska","NameEN":"","NameDE":"","NameES":"","NameFR":"","NameIT":"","NameRU":""},{"Id":"49069211","CountryCode":"PL","Name":"Stefana Batorego","NameEN":"","NameDE":"","NameES":"","NameFR":"","NameIT":"","NameRU":""},{"Id":"51504264","CountryCode":"PL","Name":"Podg\u00F3rze","NameEN":"","NameDE":"","NameES":"","NameFR":"","NameIT":"","NameRU":""},{"Id":"33015150","CountryCode":"PL","Name":"Okszowska","NameEN":"","NameDE":"","NameES":"","NameFR":"","NameIT":"","NameRU":""},{"Id":"33017395","CountryCode":"PL","Name":"Aleja Przyja\u017Ani","NameEN":"","NameDE":"","NameES":"","NameFR":"","NameIT":"","NameRU":""},{"Id":"33015807","CountryCode":"PL","Name":"Hrubieszowska","NameEN":"","NameDE":"","NameES":"","NameFR":"","NameIT":"","NameRU":""},{"Id":"33016479","CountryCode":"PL","Name":"Rejowiecka","NameEN":"","NameDE":"","NameES":"","NameFR":"","NameIT":"","NameRU":""},{"Id":"33020495","CountryCode":"PL","Name":"Dzia\u0142kowa","NameEN":"","NameDE":"","NameES":"","NameFR":"","NameIT":"","NameRU":""},{"Id":"33023007","CountryCode":"PL","Name":"Wierzbowa","NameEN":"","NameDE":"","NameES":"","NameFR":"","NameIT":"","NameRU":""},{"Id":"33016388","CountryCode":"PL","Name":"Mi\u0142a","NameEN":"","NameDE":"","NameES":"","NameFR":"","NameIT":"","NameRU":""},{"Id":"33015204","CountryCode":"PL","Name":"\u017Bo\u0142nierska","NameEN":"","NameDE":"","NameES":"","NameFR":"","NameIT":"","NameRU":""},{"Id":"33032496","CountryCode":"PL","Name":"Zawad\u00F3wka","NameEN":"","NameDE":"","NameES":"","NameFR":"","NameIT":"","NameRU":""},{"Id":"174883764","CountryCode":"PL","Name":"S\u0142awi\u0119cicka","NameEN":"","NameDE":"","NameES":"","NameFR":"","NameIT":"","NameRU":""},{"Id":"121322535","CountryCode":"PL","Name":"Ligonia","NameEN":"","NameDE":"","NameES":"","NameFR":"","NameIT":"","NameRU":""},{"Id":"33014030","CountryCode":"PL","Name":"Kwiatowa","NameEN":"","NameDE":"","NameES":"","NameFR":"","NameIT":"","NameRU":""},{"Id":"33018294","CountryCode":"PL","Name":"Warzywna","NameEN":"","NameDE":"","NameES":"","NameFR":"","NameIT":"","NameRU":""},{"Id":"33035597","CountryCode":"PL","Name":"Bociania","NameEN":"","NameDE":"","NameES":"","NameFR":"","NameIT":"","NameRU":""},{"Id":"33028178","CountryCode":"PL","Name":"Malowane","NameEN":"","NameDE":"","NameES":"","NameFR":"","NameIT":"","NameRU":""},{"Id":"26088416","CountryCode":"PL","Name":"Kr\u00F3tka","NameEN":"","NameDE":"","NameES":"","NameFR":"","NameIT":"","NameRU":""},{"Id":"26088411","CountryCode":"PL","Name":"Wiejska","NameEN":"","NameDE":"","NameES":"","NameFR":"","NameIT":"","NameRU":""},{"Id":"26088621","CountryCode":"PL","Name":"Biskupa Franciszka Cedzicha","NameEN":"","NameDE":"","NameES":"","NameFR":"","NameIT":"","NameRU":""},{"Id":"225224457","CountryCode":"PL","Name":"Dolina","NameEN":"","NameDE":"","NameES":"","NameFR":"","NameIT":"","NameRU":""},{"Id":"33029287","CountryCode":"PL","Name":"Chemiczna","NameEN":"","NameDE":"","NameES":"","NameFR":"","NameIT":"","NameRU":""},{"Id":"164704844","CountryCode":"PL","Name":"Aleja Jana Paw\u0142a II","NameEN":"","NameDE":"","NameES":"","NameFR":"","NameIT":"","NameRU":""},{"Id":"121322574","CountryCode":"PL","Name":"Klasztorna","NameEN":"","NameDE":"","NameES":"","NameFR":"","NameIT":"","NameRU":""},{"Id":"229769252","CountryCode":"PL","Name":"Rynek","NameEN":"","NameDE":"","NameES":"","NameFR":"","NameIT":"","NameRU":""},{"Id":"174324530","CountryCode":"PL","Name":"Le\u015Bnicka","NameEN":"","NameDE":"","NameES":"","NameFR":"","NameIT":"","NameRU":""},{"Id":"132654510","CountryCode":"PL","Name":"Niezapominajek","NameEN":"","NameDE":"","NameES":"","NameFR":"","NameIT":"","NameRU":""},{"Id":"45818256","CountryCode":"PL","Name":"Pod Stokiem","NameEN":"","NameDE":"","NameES":"","NameFR":"","NameIT":"","NameRU":""},{"Id":"26128876","CountryCode":"PL","Name":"Marynarska","NameEN":"","NameDE":"","NameES":"","NameFR":"","NameIT":"","NameRU":""},{"Id":"86318230","CountryCode":"PL","Name":"Pylna","NameEN":"","NameDE":"","NameES":"","NameFR":"","NameIT":"","NameRU":""},{"Id":"34097015","CountryCode":"PL","Name":"Kazimierza Wy\u017Cgi","NameEN":"","NameDE":"","NameES":"","NameFR":"","NameIT":"","NameRU":""},{"Id":"31874905","CountryCode":"PL","Name":"Wiosenna","NameEN":"","NameDE":"","NameES":"","NameFR":"","NameIT":"","NameRU":""},{"Id":"24207558","CountryCode":"PL","Name":"Che\u0142mska","NameEN":"","NameDE":"","NameES":"","NameFR":"","NameIT":"","NameRU":""},{"Id":"26012674","CountryCode":"PL","Name":"Nad Zalewem","NameEN":"","NameDE":"","NameES":"","NameFR":"","NameIT":"","NameRU":""},{"Id":"45818270","CountryCode":"PL","Name":"Malownicza","NameEN":"","NameDE":"","NameES":"","NameFR":"","NameIT":"","NameRU":""},{"Id":"34097100","CountryCode":"PL","Name":"Przysz\u0142o\u015Bci","NameEN":"","NameDE":"","NameES":"","NameFR":"","NameIT":"","NameRU":""},{"Id":"163594756","CountryCode":"PL","Name":"Bronis\u0142awa Czecha","NameEN":"","NameDE":"","NameES":"","NameFR":"","NameIT":"","NameRU":""},{"Id":"41032925","CountryCode":"PL","Name":"Junacka","NameEN":"","NameDE":"","NameES":"","NameFR":"","NameIT":"","NameRU":""},{"Id":"163598448","CountryCode":"PL","Name":"O\u015Bwi\u0119cimska","NameEN":"","NameDE":"","NameES":"","NameFR":"","NameIT":"","NameRU":""},{"Id":"31875019","CountryCode":"PL","Name":"Wilczy Stok","NameEN":"","NameDE":"","NameES":"","NameFR":"","NameIT":"","NameRU":""},{"Id":"31875017","CountryCode":"PL","Name":"Rysi Stok","NameEN":"","NameDE":"","NameES":"","NameFR":"","NameIT":"","NameRU":""},{"Id":"24186905","CountryCode":"PL","Name":"Aleja Kasztanowa","NameEN":"","NameDE":"","NameES":"","NameFR":"","NameIT":"","NameRU":""},{"Id":"31874379","CountryCode":"PL","Name":"Leona Chwistka","NameEN":"","NameDE":"","NameES":"","NameFR":"","NameIT":"","NameRU":""},{"Id":"26105070","CountryCode":"PL","Name":"J\u00F3zefa Becka","NameEN":"","NameDE":"","NameES":"","NameFR":"","NameIT":"","NameRU":""},{"Id":"24207559","CountryCode":"PL","Name":"Olszanicka","NameEN":"","NameDE":"","NameES":"","NameFR":"","NameIT":"","NameRU":""},{"Id":"31874360","CountryCode":"PL","Name":"Zakamycze","NameEN":"","NameDE":"","NameES":"","NameFR":"","NameIT":"","NameRU":""},{"Id":"f7c1b597-fbc7-48b4-aa9c-09669badc73c","CountryCode":"PL","Name":"Rzepichy","NameEN":null,"NameDE":null,"NameES":null,"NameFR":null,"NameIT":null,"NameRU":null},{"Id":"31874642","CountryCode":"PL","Name":"Za Sk\u0142onem","NameEN":"","NameDE":"","NameES":"","NameFR":"","NameIT":"","NameRU":""},{"Id":"163594758","CountryCode":"PL","Name":"Jerzego Jurowicza","NameEN":"","NameDE":"","NameES":"","NameFR":"","NameIT":"","NameRU":""},{"Id":"41557005","CountryCode":"PL","Name":"Europejska","NameEN":"","NameDE":"","NameES":"","NameFR":"","NameIT":"","NameRU":""},{"Id":"33017790","CountryCode":"PL","Name":"Po\u0142aniecka","NameEN":"","NameDE":"","NameES":"","NameFR":"","NameIT":"","NameRU":""},{"Id":"236841424","CountryCode":"PL","Name":"Aleja \u015Awi\u0119tego Urbana","NameEN":"","NameDE":"","NameES":"","NameFR":"","NameIT":"","NameRU":""},{"Id":"25476550","CountryCode":"PL","Name":"Krapkowicka","NameEN":"","NameDE":"","NameES":"","NameFR":"","NameIT":"","NameRU":""},{"Id":"183206942","CountryCode":"PL","Name":"Nowa","NameEN":"","NameDE":"","NameES":"","NameFR":"","NameIT":"","NameRU":""},{"Id":"237008828","CountryCode":"PL","Name":"Romantyczna","NameEN":"","NameDE":"","NameES":"","NameFR":"","NameIT":"","NameRU":""},{"Id":"182024425","CountryCode":"PL","Name":"Marzanny","NameEN":"","NameDE":"","NameES":"","NameFR":"","NameIT":"","NameRU":""},{"Id":"33026222","CountryCode":"PL","Name":"Kasztanowa","NameEN":"","NameDE":"","NameES":"","NameFR":"","NameIT":"","NameRU":""},{"Id":"238373373","CountryCode":"PL","Name":"R\u00F3\u017C","NameEN":"","NameDE":"","NameES":"","NameFR":"","NameIT":"","NameRU":""},{"Id":"220107989","CountryCode":"PL","Name":"Wyzwolenia","NameEN":"","NameDE":"","NameES":"","NameFR":"","NameIT":"","NameRU":""},{"Id":"121322551","CountryCode":"PL","Name":"Powsta\u0144c\u00F3w","NameEN":"","NameDE":"","NameES":"","NameFR":"","NameIT":"","NameRU":""},{"Id":"33013983","CountryCode":"PL","Name":"Urocza","NameEN":"","NameDE":"","NameES":"","NameFR":"","NameIT":"","NameRU":""},{"Id":"150190708","CountryCode":"PL","Name":"Zielona","NameEN":"","NameDE":"","NameES":"","NameFR":"","NameIT":"","NameRU":""},{"Id":"236834821","CountryCode":"PL","Name":"Elsnera","NameEN":"","NameDE":"","NameES":"","NameFR":"","NameIT":"","NameRU":""},{"Id":"33014993","CountryCode":"PL","Name":"Cypriana Kamila Norwida","NameEN":"","NameDE":"","NameES":"","NameFR":"","NameIT":"","NameRU":""},{"Id":"236834822","CountryCode":"PL","Name":"Czes\u0142awa Czosnykowskiego","NameEN":"","NameDE":"","NameES":"","NameFR":"","NameIT":"","NameRU":""},{"Id":"33023633","CountryCode":"PL","Name":"Sosnowa","NameEN":"","NameDE":"","NameES":"","NameFR":"","NameIT":"","NameRU":""},{"Id":"33024142","CountryCode":"PL","Name":"Wi\u015Bniowa","NameEN":"","NameDE":"","NameES":"","NameFR":"","NameIT":"","NameRU":""},{"Id":"33018467","CountryCode":"PL","Name":"\u015Awierkowa","NameEN":"","NameDE":"","NameES":"","NameFR":"","NameIT":"","NameRU":""},{"Id":"182021513","CountryCode":"PL","Name":"Przyja\u017Ani","NameEN":"","NameDE":"","NameES":"","NameFR":"","NameIT":"","NameRU":""},{"Id":"33028906","CountryCode":"PL","Name":"Brzozowa","NameEN":"","NameDE":"","NameES":"","NameFR":"","NameIT":"","NameRU":""},{"Id":"236834820","CountryCode":"PL","Name":"Piotra \u015Awierca","NameEN":"","NameDE":"","NameES":"","NameFR":"","NameIT":"","NameRU":""},{"Id":"33032432","CountryCode":"PL","Name":"Marii Konopnickiej","NameEN":"","NameDE":"","NameES":"","NameFR":"","NameIT":"","NameRU":""},{"Id":"244360664","CountryCode":"PL","Name":"Aleja Przyjaci\u00F3\u0142 D\u00FCbendorf","NameEN":"","NameDE":"","NameES":"","NameFR":"","NameIT":"","NameRU":""},{"Id":"33020222","CountryCode":"PL","Name":"Boles\u0142awa Prusa","NameEN":"","NameDE":"","NameES":"","NameFR":"","NameIT":"","NameRU":""},{"Id":"33028477","CountryCode":"PL","Name":"Boczna","NameEN":"","NameDE":"","NameES":"","NameFR":"","NameIT":"","NameRU":""},{"Id":"33034933","CountryCode":"PL","Name":"Gabrieli Zapolskiej","NameEN":"","NameDE":"","NameES":"","NameFR":"","NameIT":"","NameRU":""},{"Id":"33018391","CountryCode":"PL","Name":"Jana Kochanowskiego","NameEN":"","NameDE":"","NameES":"","NameFR":"","NameIT":"","NameRU":""},{"Id":"33014976","CountryCode":"PL","Name":"Marii Sk\u0142odowskiej-Curie","NameEN":"","NameDE":"","NameES":"","NameFR":"","NameIT":"","NameRU":""},{"Id":"33023452","CountryCode":"PL","Name":"Astrowa","NameEN":"","NameDE":"","NameES":"","NameFR":"","NameIT":"","NameRU":""},{"Id":"33015388","CountryCode":"PL","Name":"Irysowa","NameEN":"","NameDE":"","NameES":"","NameFR":"","NameIT":"","NameRU":""},{"Id":"196722662","CountryCode":"PL","Name":"Bratkowa","NameEN":"","NameDE":"","NameES":"","NameFR":"","NameIT":"","NameRU":""},{"Id":"33031541","CountryCode":"PL","Name":"Storczykowa","NameEN":"","NameDE":"","NameES":"","NameFR":"","NameIT":"","NameRU":""},{"Id":"33030300","CountryCode":"PL","Name":"Tulipanowa","NameEN":"","NameDE":"","NameES":"","NameFR":"","NameIT":"","NameRU":""},{"Id":"33029277","CountryCode":"PL","Name":"Makowa","NameEN":"","NameDE":"","NameES":"","NameFR":"","NameIT":"","NameRU":""},{"Id":"33012873","CountryCode":"PL","Name":"W\u0142adys\u0142awa Broniewskiego","NameEN":"","NameDE":"","NameES":"","NameFR":"","NameIT":"","NameRU":""},{"Id":"196719302","CountryCode":"PL","Name":"Hugona Ko\u0142\u0142\u0105taja","NameEN":"","NameDE":"","NameES":"","NameFR":"","NameIT":"","NameRU":""},{"Id":"33019043","CountryCode":"PL","Name":"R\u00F3\u017Cana","NameEN":"","NameDE":"","NameES":"","NameFR":"","NameIT":"","NameRU":""},{"Id":"189511520","CountryCode":"PL","Name":"Piaskowa","NameEN":"","NameDE":"","NameES":"","NameFR":"","NameIT":"","NameRU":""},{"Id":"197341593","CountryCode":"PL","Name":"Fio\u0142kowa","NameEN":"","NameDE":"","NameES":"","NameFR":"","NameIT":"","NameRU":""},{"Id":"33027316","CountryCode":"PL","Name":"Aleksandra Fredry","NameEN":"","NameDE":"","NameES":"","NameFR":"","NameIT":"","NameRU":""},{"Id":"0dfd3b58-66f1-46c1-994c-533d1a2df96e","CountryCode":"PL","Name":"Hugo Ko\u0142\u0142\u0105taja","NameEN":null,"NameDE":null,"NameES":null,"NameFR":null,"NameIT":null,"NameRU":null},{"Id":"33022865","CountryCode":"PL","Name":"Konwaliowa","NameEN":"","NameDE":"","NameES":"","NameFR":"","NameIT":"","NameRU":""},{"Id":"182021497","CountryCode":"PL","Name":"Przyjaci\u00F3\u0142 Schongau","NameEN":"","NameDE":"","NameES":"","NameFR":"","NameIT":"","NameRU":""},{"Id":"33012997","CountryCode":"PL","Name":"Sadowa","NameEN":"","NameDE":"","NameES":"","NameFR":"","NameIT":"","NameRU":""},{"Id":"26088916","CountryCode":"PL","Name":"Kamienna","NameEN":"","NameDE":"","NameES":"","NameFR":"","NameIT":"","NameRU":""},{"Id":"33016348","CountryCode":"PL","Name":"Stefana \u017Beromskiego","NameEN":"","NameDE":"","NameES":"","NameFR":"","NameIT":"","NameRU":""},{"Id":"23708837","CountryCode":"PL","Name":"Jana Matejki","NameEN":"","NameDE":"","NameES":"","NameFR":"","NameIT":"","NameRU":""},{"Id":"236841246","CountryCode":"PL","Name":"Johanna Krolla","NameEN":"","NameDE":"","NameES":"","NameFR":"","NameIT":"","NameRU":""},{"Id":"23708839","CountryCode":"PL","Name":"Juliusza S\u0142owackiego","NameEN":"","NameDE":"","NameES":"","NameFR":"","NameIT":"","NameRU":""},{"Id":"33035779","CountryCode":"PL","Name":"Adama Asnyka","NameEN":"","NameDE":"","NameES":"","NameFR":"","NameIT":"","NameRU":""},{"Id":"182021499","CountryCode":"PL","Name":"K\u0105pielowa","NameEN":"","NameDE":"","NameES":"","NameFR":"","NameIT":"","NameRU":""},{"Id":"33021354","CountryCode":"PL","Name":"Koszarowa","NameEN":"","NameDE":"","NameES":"","NameFR":"","NameIT":"","NameRU":""},{"Id":"88577506","CountryCode":"PL","Name":"Trubakowska","NameEN":"","NameDE":"","NameES":"","NameFR":"","NameIT":"","NameRU":""},{"Id":"26095307","CountryCode":"PL","Name":"Kalwaryjska","NameEN":"","NameDE":"","NameES":"","NameFR":"","NameIT":"","NameRU":""},{"Id":"174324529","CountryCode":"PL","Name":"Profesora Reinholda Olescha","NameEN":"","NameDE":"","NameES":"","NameFR":"","NameIT":"","NameRU":""},{"Id":"121322537","CountryCode":"PL","Name":"Powsta\u0144c\u00F3w \u015Al\u0105skich","NameEN":"","NameDE":"","NameES":"","NameFR":"","NameIT":"","NameRU":""},{"Id":"231903145","CountryCode":"PL","Name":"Planetorza","NameEN":"","NameDE":"","NameES":"","NameFR":"","NameIT":"","NameRU":""},{"Id":"33035692","CountryCode":"PL","Name":"Fryderyka Chopina","NameEN":"","NameDE":"","NameES":"","NameFR":"","NameIT":"","NameRU":""},{"Id":"236841242","CountryCode":"PL","Name":"Lompy","NameEN":"","NameDE":"","NameES":"","NameFR":"","NameIT":"","NameRU":""},{"Id":"236841251","CountryCode":"PL","Name":"J\u00F3zefa Bema","NameEN":"","NameDE":"","NameES":"","NameFR":"","NameIT":"","NameRU":""},{"Id":"167366934","CountryCode":"PL","Name":"Plac Dworcowy","NameEN":"","NameDE":"","NameES":"","NameFR":"","NameIT":"","NameRU":""},{"Id":"182021517","CountryCode":"PL","Name":"Zamkni\u0119ta","NameEN":"","NameDE":"","NameES":"","NameFR":"","NameIT":"","NameRU":""},{"Id":"182021514","CountryCode":"PL","Name":"Pasieczna","NameEN":"","NameDE":"","NameES":"","NameFR":"","NameIT":"","NameRU":""},{"Id":"182021509","CountryCode":"PL","Name":"Bagienna","NameEN":"","NameDE":"","NameES":"","NameFR":"","NameIT":"","NameRU":""},{"Id":"121786194","CountryCode":"PL","Name":"Wapienna","NameEN":"","NameDE":"","NameES":"","NameFR":"","NameIT":"","NameRU":""},{"Id":"33017573","CountryCode":"PL","Name":"W\u0105ska","NameEN":"","NameDE":"","NameES":"","NameFR":"","NameIT":"","NameRU":""},{"Id":"33024245","CountryCode":"PL","Name":"Jasna","NameEN":"","NameDE":"","NameES":"","NameFR":"","NameIT":"","NameRU":""},{"Id":"259024761","CountryCode":"PL","Name":"Mali\u0144ska","NameEN":"","NameDE":"","NameES":"","NameFR":"","NameIT":"","NameRU":""},{"Id":"237069857","CountryCode":"PL","Name":"Torowa","NameEN":"","NameDE":"","NameES":"","NameFR":"","NameIT":"","NameRU":""},{"Id":"121467601","CountryCode":"PL","Name":"Gogoli\u0144ska","NameEN":"","NameDE":"","NameES":"","NameFR":"","NameIT":"","NameRU":""},{"Id":"172292861","CountryCode":"PL","Name":"\u0141\u0105kowa","NameEN":"","NameDE":"","NameES":"","NameFR":"","NameIT":"","NameRU":""},{"Id":"106445269","CountryCode":"PL","Name":"Fabryczna","NameEN":"","NameDE":"","NameES":"","NameFR":"","NameIT":"","NameRU":""},{"Id":"245708003","CountryCode":"PL","Name":"Paw\u0142a","NameEN":"","NameDE":"","NameES":"","NameFR":"","NameIT":"","NameRU":""},{"Id":"189638506","CountryCode":"PL","Name":"M\u0142y\u0144ska","NameEN":"","NameDE":"","NameES":"","NameFR":"","NameIT":"","NameRU":""},{"Id":"182024438","CountryCode":"PL","Name":"D\u0119bowa","NameEN":"","NameDE":"","NameES":"","NameFR":"","NameIT":"","NameRU":""},{"Id":"237035169","CountryCode":"PL","Name":"Ksi\u0119dza Stanis\u0142awa Schulza","NameEN":"","NameDE":"","NameES":"","NameFR":"","NameIT":"","NameRU":""},{"Id":"196858303","CountryCode":"PL","Name":"Boles\u0142awa Chrobrego","NameEN":"","NameDE":"","NameES":"","NameFR":"","NameIT":"","NameRU":""},{"Id":"33015334","CountryCode":"PL","Name":"Spacerowa","NameEN":"","NameDE":"","NameES":"","NameFR":"","NameIT":"","NameRU":""},{"Id":"189511512","CountryCode":"PL","Name":"Dolna","NameEN":"","NameDE":"","NameES":"","NameFR":"","NameIT":"","NameRU":""},{"Id":"189512766","CountryCode":"PL","Name":"Nak\u0142o","NameEN":"","NameDE":"","NameES":"","NameFR":"","NameIT":"","NameRU":""},{"Id":"189511515","CountryCode":"PL","Name":"Nogowczycka","NameEN":"","NameDE":"","NameES":"","NameFR":"","NameIT":"","NameRU":""},{"Id":"189511519","CountryCode":"PL","Name":"Osiedlowa","NameEN":"","NameDE":"","NameES":"","NameFR":"","NameIT":"","NameRU":""},{"Id":"207179194","CountryCode":"PL","Name":"Skalna","NameEN":"","NameDE":"","NameES":"","NameFR":"","NameIT":"","NameRU":""},{"Id":"173405692","CountryCode":"PL","Name":"Ska\u0142y","NameEN":"","NameDE":"","NameES":"","NameFR":"","NameIT":"","NameRU":""},{"Id":"189505172","CountryCode":"PL","Name":"Szklarnia","NameEN":"","NameDE":"","NameES":"","NameFR":"","NameIT":"","NameRU":""},{"Id":"159401908","CountryCode":"PL","Name":"\u015Awibska","NameEN":"","NameDE":"","NameES":"","NameFR":"","NameIT":"","NameRU":""},{"Id":"248317699","CountryCode":"PL","Name":"Henryka Henkla","NameEN":"","NameDE":"","NameES":"","NameFR":"","NameIT":"","NameRU":""},{"Id":"189503491","CountryCode":"PL","Name":"Gromadzka","NameEN":"","NameDE":"","NameES":"","NameFR":"","NameIT":"","NameRU":""},{"Id":"189503493","CountryCode":"PL","Name":"Kotuli\u0144ska","NameEN":"","NameDE":"","NameES":"","NameFR":"","NameIT":"","NameRU":""},{"Id":"189503496","CountryCode":"PL","Name":"Proboszczowicka","NameEN":"","NameDE":"","NameES":"","NameFR":"","NameIT":"","NameRU":""},{"Id":"189503494","CountryCode":"PL","Name":"Niekarmska","NameEN":"","NameDE":"","NameES":"","NameFR":"","NameIT":"","NameRU":""},{"Id":"189503500","CountryCode":"PL","Name":"Zalesie","NameEN":"","NameDE":"","NameES":"","NameFR":"","NameIT":"","NameRU":""},{"Id":"189532218","CountryCode":"PL","Name":"Na Buczek","NameEN":"","NameDE":"","NameES":"","NameFR":"","NameIT":"","NameRU":""},{"Id":"169995802","CountryCode":"PL","Name":"Towarowa","NameEN":"","NameDE":"","NameES":"","NameFR":"","NameIT":"","NameRU":""},{"Id":"258951587","CountryCode":"PL","Name":"Podg\u00F3rna","NameEN":"","NameDE":"","NameES":"","NameFR":"","NameIT":"","NameRU":""},{"Id":"259032712","CountryCode":"PL","Name":"Ciemna","NameEN":"","NameDE":"","NameES":"","NameFR":"","NameIT":"","NameRU":""},{"Id":"150190704","CountryCode":"PL","Name":"Ujazdowska","NameEN":"","NameDE":"","NameES":"","NameFR":"","NameIT":"","NameRU":""},{"Id":"110528435","CountryCode":"PL","Name":"Wojska Polskiego","NameEN":"","NameDE":"","NameES":"","NameFR":"","NameIT":"","NameRU":""},{"Id":"182222954","CountryCode":"PL","Name":"Kozielska","NameEN":"","NameDE":"","NameES":"","NameFR":"","NameIT":"","NameRU":""},{"Id":"237048534","CountryCode":"PL","Name":"Czere\u015Bniowa","NameEN":"","NameDE":"","NameES":"","NameFR":"","NameIT":"","NameRU":""},{"Id":"359507163","CountryCode":"PL","Name":"Rolna","NameEN":"","NameDE":"","NameES":"","NameFR":"","NameIT":"","NameRU":""},{"Id":"236843165","CountryCode":"PL","Name":"Rybacka","NameEN":"","NameDE":"","NameES":"","NameFR":"","NameIT":"","NameRU":""},{"Id":"810257885","CountryCode":"PL","Name":"Ksi\u0119dza Kozio\u0142ka","NameEN":"","NameDE":"","NameES":"","NameFR":"","NameIT":"","NameRU":""},{"Id":"23708838","CountryCode":"PL","Name":"3 Maja","NameEN":"","NameDE":"","NameES":"","NameFR":"","NameIT":"","NameRU":""},{"Id":"33024340","CountryCode":"PL","Name":"Kardyna\u0142a Stefana Wyszy\u0144skiego","NameEN":"","NameDE":"","NameES":"","NameFR":"","NameIT":"","NameRU":""},{"Id":"237068025","CountryCode":"PL","Name":"Strzebni\u00F3w","NameEN":"","NameDE":"","NameES":"","NameFR":"","NameIT":"","NameRU":""},{"Id":"182025496","CountryCode":"PL","Name":"Plebiscytowa","NameEN":"","NameDE":"","NameES":"","NameFR":"","NameIT":"","NameRU":""},{"Id":"238085351","CountryCode":"PL","Name":"Opolska","NameEN":"","NameDE":"","NameES":"","NameFR":"","NameIT":"","NameRU":""},{"Id":"33027025","CountryCode":"PL","Name":"Wodna","NameEN":"","NameDE":"","NameES":"","NameFR":"","NameIT":"","NameRU":""},{"Id":"150190700","CountryCode":"PL","Name":"G\u0142\u00F3wna","NameEN":"","NameDE":"","NameES":"","NameFR":"","NameIT":"","NameRU":""},{"Id":"23708877","CountryCode":"PL","Name":"Adama Mickiewicza","NameEN":"","NameDE":"","NameES":"","NameFR":"","NameIT":"","NameRU":""},{"Id":"33025281","CountryCode":"PL","Name":"Plac Tadeusza Ko\u015Bciuszki","NameEN":"","NameDE":"","NameES":"","NameFR":"","NameIT":"","NameRU":""},{"Id":"33014827","CountryCode":"PL","Name":"Aleja 3 Maja","NameEN":"","NameDE":"","NameES":"","NameFR":"","NameIT":"","NameRU":""},{"Id":"cb966c53-5364-4de1-b72a-7950cb1cb8cc","CountryCode":"PL","Name":"Plac Doktora Edwarda \u0141uczkowskiego","NameEN":null,"NameDE":null,"NameES":null,"NameFR":null,"NameIT":null,"NameRU":null},{"Id":"215364821","CountryCode":"PL","Name":"Rampa Brzeska","NameEN":"","NameDE":"","NameES":"","NameFR":"","NameIT":"","NameRU":""},{"Id":"33012413","CountryCode":"PL","Name":"Hutnicza","NameEN":"","NameDE":"","NameES":"","NameFR":"","NameIT":"","NameRU":""},{"Id":"33019913","CountryCode":"PL","Name":"Genera\u0142a Gustawa Orlicz-Dreszera","NameEN":"","NameDE":"","NameES":"","NameFR":"","NameIT":"","NameRU":""},{"Id":"302964779","CountryCode":"PL","Name":"Ceramiczna","NameEN":"","NameDE":"","NameES":"","NameFR":"","NameIT":"","NameRU":""},{"Id":"33033078","CountryCode":"PL","Name":"Przemys\u0142owa","NameEN":"","NameDE":"","NameES":"","NameFR":"","NameIT":"","NameRU":""},{"Id":"33019600","CountryCode":"PL","Name":"Aleja Marsza\u0142ka J\u00F3zefa Pi\u0142sudskiego","NameEN":"","NameDE":"","NameES":"","NameFR":"","NameIT":"","NameRU":""},{"Id":"33020805","CountryCode":"PL","Name":"1. Pu\u0142ku Szwole\u017Cer\u00F3w","NameEN":"","NameDE":"","NameES":"","NameFR":"","NameIT":"","NameRU":""},{"Id":"33012573","CountryCode":"PL","Name":"Staro\u015Bci\u0144ska","NameEN":"","NameDE":"","NameES":"","NameFR":"","NameIT":"","NameRU":""},{"Id":"33034977","CountryCode":"PL","Name":"Jedno\u015B\u0107","NameEN":"","NameDE":"","NameES":"","NameFR":"","NameIT":"","NameRU":""},{"Id":"33028388","CountryCode":"PL","Name":"Wojs\u0142awicka","NameEN":"","NameDE":"","NameES":"","NameFR":"","NameIT":"","NameRU":""},{"Id":"309141096","CountryCode":"PL","Name":"Lwowska B","NameEN":"","NameDE":"","NameES":"","NameFR":"","NameIT":"","NameRU":""},{"Id":"196994717","CountryCode":"PL","Name":"Ksi\u0119dza Marcelego Mrozka","NameEN":"","NameDE":"","NameES":"","NameFR":"","NameIT":"","NameRU":""},{"Id":"33017799","CountryCode":"PL","Name":"Boles\u0142awa Wirskiego","NameEN":"","NameDE":"","NameES":"","NameFR":"","NameIT":"","NameRU":""},{"Id":"33026100","CountryCode":"PL","Name":"Karola Szymanowskiego","NameEN":"","NameDE":"","NameES":"","NameFR":"","NameIT":"","NameRU":""},{"Id":"33020095","CountryCode":"PL","Name":"Henryka Wieniawskiego","NameEN":"","NameDE":"","NameES":"","NameFR":"","NameIT":"","NameRU":""},{"Id":"33020110","CountryCode":"PL","Name":"Witolda Lutos\u0142awskiego","NameEN":"","NameDE":"","NameES":"","NameFR":"","NameIT":"","NameRU":""},{"Id":"397272119","CountryCode":"PL","Name":"Karola Kurpi\u0144skiego","NameEN":"","NameDE":"","NameES":"","NameFR":"","NameIT":"","NameRU":""},{"Id":"33027864","CountryCode":"PL","Name":"Szarych Szereg\u00F3w","NameEN":"","NameDE":"","NameES":"","NameFR":"","NameIT":"","NameRU":""},{"Id":"33029166","CountryCode":"PL","Name":"Genera\u0142a W\u0142adys\u0142awa Andersa","NameEN":"","NameDE":"","NameES":"","NameFR":"","NameIT":"","NameRU":""},{"Id":"33034990","CountryCode":"PL","Name":"Genera\u0142a Stanis\u0142awa Maczka","NameEN":"","NameDE":"","NameES":"","NameFR":"","NameIT":"","NameRU":""},{"Id":"33028417","CountryCode":"PL","Name":"Syn\u00F3w Pu\u0142ku","NameEN":"","NameDE":"","NameES":"","NameFR":"","NameIT":"","NameRU":""},{"Id":"33019475","CountryCode":"PL","Name":"Legion\u00F3w Polskich","NameEN":"","NameDE":"","NameES":"","NameFR":"","NameIT":"","NameRU":""},{"Id":"33013464","CountryCode":"PL","Name":"\u017Beglarska","NameEN":"","NameDE":"","NameES":"","NameFR":"","NameIT":"","NameRU":""},{"Id":"33026008","CountryCode":"PL","Name":"Grzegorza Piramowicza","NameEN":"","NameDE":"","NameES":"","NameFR":"","NameIT":"","NameRU":""},{"Id":"33032284","CountryCode":"PL","Name":"Malinowa","NameEN":"","NameDE":"","NameES":"","NameFR":"","NameIT":"","NameRU":""},{"Id":"33029391","CountryCode":"PL","Name":"Po\u0142udniowa","NameEN":"","NameDE":"","NameES":"","NameFR":"","NameIT":"","NameRU":""},{"Id":"33021754","CountryCode":"PL","Name":"Pogodna","NameEN":"","NameDE":"","NameES":"","NameFR":"","NameIT":"","NameRU":""},{"Id":"33036042","CountryCode":"PL","Name":"Miernicza","NameEN":"","NameDE":"","NameES":"","NameFR":"","NameIT":"","NameRU":""},{"Id":"51200458","CountryCode":"PL","Name":"Plac Kupiecki","NameEN":"","NameDE":"","NameES":"","NameFR":"","NameIT":"","NameRU":""},{"Id":"33033076","CountryCode":"PL","Name":"Ksi\u0119dza Jerzego Popie\u0142uszki","NameEN":"","NameDE":"","NameES":"","NameFR":"","NameIT":"","NameRU":""},{"Id":"60266436","CountryCode":"PL","Name":"Pocztowa","NameEN":"","NameDE":"","NameES":"","NameFR":"","NameIT":"","NameRU":""},{"Id":"33034932","CountryCode":"PL","Name":"Sybirak\u00F3w","NameEN":"","NameDE":"","NameES":"","NameFR":"","NameIT":"","NameRU":""},{"Id":"33013274","CountryCode":"PL","Name":"Siedlecka","NameEN":"","NameDE":"","NameES":"","NameFR":"","NameIT":"","NameRU":""},{"Id":"33034651","CountryCode":"PL","Name":"Zamojska","NameEN":"","NameDE":"","NameES":"","NameFR":"","NameIT":"","NameRU":""},{"Id":"33020698","CountryCode":"PL","Name":"Gabriela Narutowicza","NameEN":"","NameDE":"","NameES":"","NameFR":"","NameIT":"","NameRU":""},{"Id":"33015840","CountryCode":"PL","Name":"Krokusowa","NameEN":"","NameDE":"","NameES":"","NameFR":"","NameIT":"","NameRU":""},{"Id":"33033948","CountryCode":"PL","Name":"Kaflarska","NameEN":"","NameDE":"","NameES":"","NameFR":"","NameIT":"","NameRU":""},{"Id":"33025804","CountryCode":"PL","Name":"Narcyzowa","NameEN":"","NameDE":"","NameES":"","NameFR":"","NameIT":"","NameRU":""},{"Id":"33015585","CountryCode":"PL","Name":"Azaliowa","NameEN":"","NameDE":"","NameES":"","NameFR":"","NameIT":"","NameRU":""},{"Id":"33017896","CountryCode":"PL","Name":"Szarotki","NameEN":"","NameDE":"","NameES":"","NameFR":"","NameIT":"","NameRU":""},{"Id":"33016159","CountryCode":"PL","Name":"Ja\u015Bminowa","NameEN":"","NameDE":"","NameES":"","NameFR":"","NameIT":"","NameRU":""},{"Id":"33033153","CountryCode":"PL","Name":"J\u00F3zefa Che\u0142mo\u0144skiego","NameEN":"","NameDE":"","NameES":"","NameFR":"","NameIT":"","NameRU":""},{"Id":"33034792","CountryCode":"PL","Name":"Wrzosowa","NameEN":"","NameDE":"","NameES":"","NameFR":"","NameIT":"","NameRU":""},{"Id":"764141225","CountryCode":"PL","Name":"U\u0142an\u00F3w","NameEN":"","NameDE":"","NameES":"","NameFR":"","NameIT":"","NameRU":""},{"Id":"33021910","CountryCode":"PL","Name":"Stanis\u0142awa Wyspia\u0144skiego","NameEN":"","NameDE":"","NameES":"","NameFR":"","NameIT":"","NameRU":""},{"Id":"33029905","CountryCode":"PL","Name":"Pu\u0142awska","NameEN":"","NameDE":"","NameES":"","NameFR":"","NameIT":"","NameRU":""},{"Id":"149780344","CountryCode":"PL","Name":"W\u0142odawska","NameEN":"","NameDE":"","NameES":"","NameFR":"","NameIT":"","NameRU":""},{"Id":"33012858","CountryCode":"PL","Name":"Kra\u0144cowa","NameEN":"","NameDE":"","NameES":"","NameFR":"","NameIT":"","NameRU":""},{"Id":"33034322","CountryCode":"PL","Name":"W\u0142adys\u0142awa G\u0142owackiego","NameEN":"","NameDE":"","NameES":"","NameFR":"","NameIT":"","NameRU":""},{"Id":"33030314","CountryCode":"PL","Name":"Kazimierza Bogdanowicza","NameEN":"","NameDE":"","NameES":"","NameFR":"","NameIT":"","NameRU":""},{"Id":"33014047","CountryCode":"PL","Name":"Wandy Orli\u0144skiej","NameEN":"","NameDE":"","NameES":"","NameFR":"","NameIT":"","NameRU":""},{"Id":"33011823","CountryCode":"PL","Name":"Wincentego Zygmunta","NameEN":"","NameDE":"","NameES":"","NameFR":"","NameIT":"","NameRU":""},{"Id":"33020674","CountryCode":"PL","Name":"Budowlana","NameEN":"","NameDE":"","NameES":"","NameFR":"","NameIT":"","NameRU":""},{"Id":"305326695","CountryCode":"PL","Name":"Wielkopolska","NameEN":"","NameDE":"","NameES":"","NameFR":"","NameIT":"","NameRU":""},{"Id":"33015177","CountryCode":"PL","Name":"Poleska","NameEN":"","NameDE":"","NameES":"","NameFR":"","NameIT":"","NameRU":""},{"Id":"33028285","CountryCode":"PL","Name":"Wygon","NameEN":"","NameDE":"","NameES":"","NameFR":"","NameIT":"","NameRU":""},{"Id":"196826051","CountryCode":"PL","Name":"Bursztynowa","NameEN":"","NameDE":"","NameES":"","NameFR":"","NameIT":"","NameRU":""},{"Id":"33016142","CountryCode":"PL","Name":"J\u00F3zefa Ignacego Kraszewskiego","NameEN":"","NameDE":"","NameES":"","NameFR":"","NameIT":"","NameRU":""},{"Id":"33027970","CountryCode":"PL","Name":"Wojciecha Kossaka","NameEN":"","NameDE":"","NameES":"","NameFR":"","NameIT":"","NameRU":""},{"Id":"33036136","CountryCode":"PL","Name":"Juliana Tuwima","NameEN":"","NameDE":"","NameES":"","NameFR":"","NameIT":"","NameRU":""},{"Id":"33011861","CountryCode":"PL","Name":"Oskara Kolberga","NameEN":"","NameDE":"","NameES":"","NameFR":"","NameIT":"","NameRU":""},{"Id":"33024215","CountryCode":"PL","Name":"Ignacego Krasickiego","NameEN":"","NameDE":"","NameES":"","NameFR":"","NameIT":"","NameRU":""},{"Id":"33031451","CountryCode":"PL","Name":"Doktora Judyma","NameEN":"","NameDE":"","NameES":"","NameFR":"","NameIT":"","NameRU":""},{"Id":"33027959","CountryCode":"PL","Name":"Kalinowa","NameEN":"","NameDE":"","NameES":"","NameFR":"","NameIT":"","NameRU":""},{"Id":"33014597","CountryCode":"PL","Name":"Diamentowa","NameEN":"","NameDE":"","NameES":"","NameFR":"","NameIT":"","NameRU":""},{"Id":"305743852","CountryCode":"PL","Name":"Rubinowa","NameEN":"","NameDE":"","NameES":"","NameFR":"","NameIT":"","NameRU":""},{"Id":"33033562","CountryCode":"PL","Name":"Ch\u0142odna","NameEN":"","NameDE":"","NameES":"","NameFR":"","NameIT":"","NameRU":""},{"Id":"33025502","CountryCode":"PL","Name":"Zak\u0105tek","NameEN":"","NameDE":"","NameES":"","NameFR":"","NameIT":"","NameRU":""},{"Id":"33027808","CountryCode":"PL","Name":"Nadrzeczna","NameEN":"","NameDE":"","NameES":"","NameFR":"","NameIT":"","NameRU":""},{"Id":"33023746","CountryCode":"PL","Name":"\u0141\u0105czna","NameEN":"","NameDE":"","NameES":"","NameFR":"","NameIT":"","NameRU":""},{"Id":"33025315","CountryCode":"PL","Name":"P\u00F3\u0142nocna","NameEN":"","NameDE":"","NameES":"","NameFR":"","NameIT":"","NameRU":""},{"Id":"33030140","CountryCode":"PL","Name":"Browarna","NameEN":"","NameDE":"","NameES":"","NameFR":"","NameIT":"","NameRU":""},{"Id":"33016344","CountryCode":"PL","Name":"Piekarska","NameEN":"","NameDE":"","NameES":"","NameFR":"","NameIT":"","NameRU":""},{"Id":"33025747","CountryCode":"PL","Name":"Zygmunta Szymczakowskiego","NameEN":"","NameDE":"","NameES":"","NameFR":"","NameIT":"","NameRU":""},{"Id":"189636962","CountryCode":"PL","Name":"Utrata","NameEN":"","NameDE":"","NameES":"","NameFR":"","NameIT":"","NameRU":""},{"Id":"271071843","CountryCode":"PL","Name":"Ga\u0107","NameEN":"","NameDE":"","NameES":"","NameFR":"","NameIT":"","NameRU":""},{"Id":"23708585","CountryCode":"PL","Name":"Pyskowicka","NameEN":"","NameDE":"","NameES":"","NameFR":"","NameIT":"","NameRU":""},{"Id":"208689100","CountryCode":"PL","Name":"Osiedle Goj","NameEN":"","NameDE":"","NameES":"","NameFR":"","NameIT":"","NameRU":""},{"Id":"189828054","CountryCode":"PL","Name":"Stod\u00F3\u0142ka","NameEN":"","NameDE":"","NameES":"","NameFR":"","NameIT":"","NameRU":""},{"Id":"189638501","CountryCode":"PL","Name":"Klubowa","NameEN":"","NameDE":"","NameES":"","NameFR":"","NameIT":"","NameRU":""},{"Id":"189638502","CountryCode":"PL","Name":"K\u0142odnicka","NameEN":"","NameDE":"","NameES":"","NameFR":"","NameIT":"","NameRU":""},{"Id":"189636945","CountryCode":"PL","Name":"Na Zakr\u0119cie","NameEN":"","NameDE":"","NameES":"","NameFR":"","NameIT":"","NameRU":""},{"Id":"189637315","CountryCode":"PL","Name":"Owocowa","NameEN":"","NameDE":"","NameES":"","NameFR":"","NameIT":"","NameRU":""},{"Id":"249007774","CountryCode":"PL","Name":"Poddworcowa","NameEN":"","NameDE":"","NameES":"","NameFR":"","NameIT":"","NameRU":""},{"Id":"23708608","CountryCode":"PL","Name":"Dworcowa","NameEN":"","NameDE":"","NameES":"","NameFR":"","NameIT":"","NameRU":""},{"Id":"33015038","CountryCode":"PL","Name":"Ksi\u0119dza Zygfryda Berezeckiego","NameEN":"","NameDE":"","NameES":"","NameFR":"","NameIT":"","NameRU":""},{"Id":"33011878","CountryCode":"PL","Name":"Grunwaldzka","NameEN":"","NameDE":"","NameES":"","NameFR":"","NameIT":"","NameRU":""},{"Id":"33025786","CountryCode":"PL","Name":"\u017Babia","NameEN":"","NameDE":"","NameES":"","NameFR":"","NameIT":"","NameRU":""},{"Id":"33024851","CountryCode":"PL","Name":"Przejazdowa","NameEN":"","NameDE":"","NameES":"","NameFR":"","NameIT":"","NameRU":""},{"Id":"33028086","CountryCode":"PL","Name":"Majdan","NameEN":"","NameDE":"","NameES":"","NameFR":"","NameIT":"","NameRU":""},{"Id":"197336540","CountryCode":"PL","Name":"Doktor Barbary Sztembis","NameEN":"","NameDE":"","NameES":"","NameFR":"","NameIT":"","NameRU":""},{"Id":"196844718","CountryCode":"PL","Name":"\u017Burawia","NameEN":"","NameDE":"","NameES":"","NameFR":"","NameIT":"","NameRU":""},{"Id":"33023393","CountryCode":"PL","Name":"Pszenna","NameEN":"","NameDE":"","NameES":"","NameFR":"","NameIT":"","NameRU":""},{"Id":"33025692","CountryCode":"PL","Name":"Szpakowa","NameEN":"","NameDE":"","NameES":"","NameFR":"","NameIT":"","NameRU":""},{"Id":"391966396","CountryCode":"PL","Name":"W\u0142adys\u0142awa Jagie\u0142\u0142y","NameEN":"","NameDE":"","NameES":"","NameFR":"","NameIT":"","NameRU":""},{"Id":"197355260","CountryCode":"PL","Name":"Ireny Stanis\u0142awskiej","NameEN":"","NameDE":"","NameES":"","NameFR":"","NameIT":"","NameRU":""},{"Id":"196855794","CountryCode":"PL","Name":"\u015Awi\u0119tej Jadwigi Kr\u00F3lowej","NameEN":"","NameDE":"","NameES":"","NameFR":"","NameIT":"","NameRU":""},{"Id":"33015212","CountryCode":"PL","Name":"Bednarska","NameEN":"","NameDE":"","NameES":"","NameFR":"","NameIT":"","NameRU":""},{"Id":"33015511","CountryCode":"PL","Name":"S\u0142owicza","NameEN":"","NameDE":"","NameES":"","NameFR":"","NameIT":"","NameRU":""},{"Id":"33027248","CountryCode":"PL","Name":"Piwna","NameEN":"","NameDE":"","NameES":"","NameFR":"","NameIT":"","NameRU":""},{"Id":"75412708","CountryCode":"PL","Name":"Metalowa","NameEN":"","NameDE":"","NameES":"","NameFR":"","NameIT":"","NameRU":""},{"Id":"33022255","CountryCode":"PL","Name":"Rusa\u0142ki","NameEN":"","NameDE":"","NameES":"","NameFR":"","NameIT":"","NameRU":""},{"Id":"33021844","CountryCode":"PL","Name":"Niska","NameEN":"","NameDE":"","NameES":"","NameFR":"","NameIT":"","NameRU":""},{"Id":"33034921","CountryCode":"PL","Name":"M\u0142ynarska","NameEN":"","NameDE":"","NameES":"","NameFR":"","NameIT":"","NameRU":""},{"Id":"33031231","CountryCode":"PL","Name":"Nadtorowa","NameEN":"","NameDE":"","NameES":"","NameFR":"","NameIT":"","NameRU":""},{"Id":"33020317","CountryCode":"PL","Name":"Marii Rodziewicz\u00F3wny","NameEN":"","NameDE":"","NameES":"","NameFR":"","NameIT":"","NameRU":""},{"Id":"33027848","CountryCode":"PL","Name":"Maryli Wolskiej","NameEN":"","NameDE":"","NameES":"","NameFR":"","NameIT":"","NameRU":""},{"Id":"915117321","CountryCode":"PL","Name":"Mariana Pilarskiego","NameEN":"","NameDE":"","NameES":"","NameFR":"","NameIT":"","NameRU":""},{"Id":"33029109","CountryCode":"PL","Name":"Kowalska","NameEN":"","NameDE":"","NameES":"","NameFR":"","NameIT":"","NameRU":""},{"Id":"33032243","CountryCode":"PL","Name":"K\u0105pieliskowa","NameEN":"","NameDE":"","NameES":"","NameFR":"","NameIT":"","NameRU":""},{"Id":"231341000","CountryCode":"PL","Name":"Genera\u0142a Stanis\u0142awa Skalskiego","NameEN":"","NameDE":"","NameES":"","NameFR":"","NameIT":"","NameRU":""},{"Id":"196857199","CountryCode":"PL","Name":"Mokra","NameEN":"","NameDE":"","NameES":"","NameFR":"","NameIT":"","NameRU":""},{"Id":"197339166","CountryCode":"PL","Name":"\u0141ab\u0119dzia","NameEN":"","NameDE":"","NameES":"","NameFR":"","NameIT":"","NameRU":""},{"Id":"303890217","CountryCode":"PL","Name":"Henryka Wiercie\u0144skiego","NameEN":"","NameDE":"","NameES":"","NameFR":"","NameIT":"","NameRU":""},{"Id":"33018097","CountryCode":"PL","Name":"Genera\u0142a J\u00F3zefa Wybickiego","NameEN":"","NameDE":"","NameES":"","NameFR":"","NameIT":"","NameRU":""},{"Id":"33012669","CountryCode":"PL","Name":"Genera\u0142a Jaros\u0142awa D\u0105browskiego","NameEN":"","NameDE":"","NameES":"","NameFR":"","NameIT":"","NameRU":""},{"Id":"33015869","CountryCode":"PL","Name":"Emilii Plater","NameEN":"","NameDE":"","NameES":"","NameFR":"","NameIT":"","NameRU":""},{"Id":"33015555","CountryCode":"PL","Name":"Jana Brzechwy","NameEN":"","NameDE":"","NameES":"","NameFR":"","NameIT":"","NameRU":""},{"Id":"33029998","CountryCode":"PL","Name":"Tadeusza Reytana","NameEN":"","NameDE":"","NameES":"","NameFR":"","NameIT":"","NameRU":""},{"Id":"33015171","CountryCode":"PL","Name":"Antonin","NameEN":"","NameDE":"","NameES":"","NameFR":"","NameIT":"","NameRU":""},{"Id":"33018493","CountryCode":"PL","Name":"Modrzewiowa","NameEN":"","NameDE":"","NameES":"","NameFR":"","NameIT":"","NameRU":""},{"Id":"33017848","CountryCode":"PL","Name":"Wolwin\u00F3w","NameEN":"","NameDE":"","NameES":"","NameFR":"","NameIT":"","NameRU":""},{"Id":"33029445","CountryCode":"PL","Name":"Rac\u0142awicka","NameEN":"","NameDE":"","NameES":"","NameFR":"","NameIT":"","NameRU":""},{"Id":"33014486","CountryCode":"PL","Name":"\u0141owiecka","NameEN":"","NameDE":"","NameES":"","NameFR":"","NameIT":"","NameRU":""},{"Id":"33014509","CountryCode":"PL","Name":"Jaworowa","NameEN":"","NameDE":"","NameES":"","NameFR":"","NameIT":"","NameRU":""},{"Id":"33014590","CountryCode":"PL","Name":"Stanis\u0142awa Staszica","NameEN":"","NameDE":"","NameES":"","NameFR":"","NameIT":"","NameRU":""},{"Id":"33035759","CountryCode":"PL","Name":"Rolnicza","NameEN":"","NameDE":"","NameES":"","NameFR":"","NameIT":"","NameRU":""},{"Id":"33013317","CountryCode":"PL","Name":"Zielna","NameEN":"","NameDE":"","NameES":"","NameFR":"","NameIT":"","NameRU":""},{"Id":"33015795","CountryCode":"PL","Name":"Wile\u0144ska","NameEN":"","NameDE":"","NameES":"","NameFR":"","NameIT":"","NameRU":""},{"Id":"33017821","CountryCode":"PL","Name":"U\u015Bci\u0142ugska","NameEN":"","NameDE":"","NameES":"","NameFR":"","NameIT":"","NameRU":""},{"Id":"33013079","CountryCode":"PL","Name":"Sp\u00F3\u0142dzielcza","NameEN":"","NameDE":"","NameES":"","NameFR":"","NameIT":"","NameRU":""},{"Id":"33030556","CountryCode":"PL","Name":"Czerwonego Krzy\u017Ca","NameEN":"","NameDE":"","NameES":"","NameFR":"","NameIT":"","NameRU":""},{"Id":"33027552","CountryCode":"PL","Name":"Elizy Orzeszkowej","NameEN":"","NameDE":"","NameES":"","NameFR":"","NameIT":"","NameRU":""},{"Id":"33021316","CountryCode":"PL","Name":"Henryka Jordana","NameEN":"","NameDE":"","NameES":"","NameFR":"","NameIT":"","NameRU":""},{"Id":"33036069","CountryCode":"PL","Name":"Micha\u0142a Ki\u0144czyka","NameEN":"","NameDE":"","NameES":"","NameFR":"","NameIT":"","NameRU":""},{"Id":"33024561","CountryCode":"PL","Name":"Janusza Korczaka","NameEN":"","NameDE":"","NameES":"","NameFR":"","NameIT":"","NameRU":""},{"Id":"160a47d5-c525-4810-9604-3ee92112a33a","CountryCode":"PL","Name":"Dorohuska","NameEN":null,"NameDE":null,"NameES":null,"NameFR":null,"NameIT":null,"NameRU":null},{"Id":"33023497","CountryCode":"PL","Name":"Lotnicza","NameEN":"","NameDE":"","NameES":"","NameFR":"","NameIT":"","NameRU":""},{"Id":"121322565","CountryCode":"PL","Name":"Plac My\u015Bliwca","NameEN":"","NameDE":"","NameES":"","NameFR":"","NameIT":"","NameRU":""},{"Id":"24207557","CountryCode":"PL","Name":"Pod\u0142u\u017Cna","NameEN":"","NameDE":"","NameES":"","NameFR":"","NameIT":"","NameRU":""},{"Id":"22935408","CountryCode":"PL","Name":"Strzegomska","NameEN":"","NameDE":"","NameES":"","NameFR":"","NameIT":"","NameRU":""},{"Id":"187253129","CountryCode":"PL","Name":"Mostowa","NameEN":"","NameDE":"","NameES":"","NameFR":"","NameIT":"","NameRU":""},{"Id":"172236717","CountryCode":"PL","Name":"Doli\u0144ska","NameEN":"","NameDE":"","NameES":"","NameFR":"","NameIT":"","NameRU":""},{"Id":"207178905","CountryCode":"PL","Name":"B\u0142otnicka","NameEN":"","NameDE":"","NameES":"","NameFR":"","NameIT":"","NameRU":""},{"Id":"207318568","CountryCode":"PL","Name":"Olszowska","NameEN":"","NameDE":"","NameES":"","NameFR":"","NameIT":"","NameRU":""},{"Id":"91570767","CountryCode":"PL","Name":"Centawska","NameEN":"","NameDE":"","NameES":"","NameFR":"","NameIT":"","NameRU":""},{"Id":"207176653","CountryCode":"PL","Name":"Stara Cegielnia","NameEN":"","NameDE":"","NameES":"","NameFR":"","NameIT":"","NameRU":""},{"Id":"121322577","CountryCode":"PL","Name":"Bronis\u0142awy","NameEN":"","NameDE":"","NameES":"","NameFR":"","NameIT":"","NameRU":""},{"Id":"121322549","CountryCode":"PL","Name":"1 Maja","NameEN":"","NameDE":"","NameES":"","NameFR":"","NameIT":"","NameRU":""},{"Id":"121322584","CountryCode":"PL","Name":"\u015Awi\u0119tego Jacka","NameEN":"","NameDE":"","NameES":"","NameFR":"","NameIT":"","NameRU":""},{"Id":"121786191","CountryCode":"PL","Name":"\u015Awi\u0119tego Czes\u0142awa","NameEN":"","NameDE":"","NameES":"","NameFR":"","NameIT":"","NameRU":""},{"Id":"172292795","CountryCode":"PL","Name":"Brzezi\u0144ska","NameEN":"","NameDE":"","NameES":"","NameFR":"","NameIT":"","NameRU":""},{"Id":"172292830","CountryCode":"PL","Name":"Celna","NameEN":"","NameDE":"","NameES":"","NameFR":"","NameIT":"","NameRU":""},{"Id":"121308690","CountryCode":"PL","Name":"Plac Stawowy","NameEN":"","NameDE":"","NameES":"","NameFR":"","NameIT":"","NameRU":""},{"Id":"121778762","CountryCode":"PL","Name":"Zakrzowska","NameEN":"","NameDE":"","NameES":"","NameFR":"","NameIT":"","NameRU":""},{"Id":"181335126","CountryCode":"PL","Name":"G\u00F3ry \u015Awi\u0119tej Anny","NameEN":"","NameDE":"","NameES":"","NameFR":"","NameIT":"","NameRU":""},{"Id":"230900744","CountryCode":"PL","Name":"Niwy","NameEN":"","NameDE":"","NameES":"","NameFR":"","NameIT":"","NameRU":""},{"Id":"183980520","CountryCode":"PL","Name":"Trzech Braci","NameEN":"","NameDE":"","NameES":"","NameFR":"","NameIT":"","NameRU":""},{"Id":"237343922","CountryCode":"PL","Name":"Alojzego Dambonia","NameEN":"","NameDE":"","NameES":"","NameFR":"","NameIT":"","NameRU":""},{"Id":"237343921","CountryCode":"PL","Name":"Juliusza Ligonia","NameEN":"","NameDE":"","NameES":"","NameFR":"","NameIT":"","NameRU":""},{"Id":"237343920","CountryCode":"PL","Name":"Jakuba Kani","NameEN":"","NameDE":"","NameES":"","NameFR":"","NameIT":"","NameRU":""},{"Id":"256478553","CountryCode":"PL","Name":"Osiedle XXX lecia","NameEN":"","NameDE":"","NameES":"","NameFR":"","NameIT":"","NameRU":""},{"Id":"273935576","CountryCode":"PL","Name":"Ojca Maksymiliana Marii Kolbe","NameEN":"","NameDE":"","NameES":"","NameFR":"","NameIT":"","NameRU":""},{"Id":"247259729","CountryCode":"PL","Name":"Karola Miarki","NameEN":"","NameDE":"","NameES":"","NameFR":"","NameIT":"","NameRU":""},{"Id":"256477739","CountryCode":"PL","Name":"Osiedle Sady","NameEN":"","NameDE":"","NameES":"","NameFR":"","NameIT":"","NameRU":""},{"Id":"33034982","CountryCode":"PL","Name":"Stanis\u0142awa Ma\u0142achowskiego","NameEN":"","NameDE":"","NameES":"","NameFR":"","NameIT":"","NameRU":""},{"Id":"1284371999","CountryCode":"PL","Name":"Jakuba Hudalli","NameEN":"","NameDE":"","NameES":"","NameFR":"","NameIT":"","NameRU":""},{"Id":"258974270","CountryCode":"PL","Name":"Prosta","NameEN":"","NameDE":"","NameES":"","NameFR":"","NameIT":"","NameRU":""},{"Id":"150190779","CountryCode":"PL","Name":"Jorda\u0144ska","NameEN":"","NameDE":"","NameES":"","NameFR":"","NameIT":"","NameRU":""},{"Id":"204844896","CountryCode":"PL","Name":"Cmentarna","NameEN":"","NameDE":"","NameES":"","NameFR":"","NameIT":"","NameRU":""},{"Id":"33013562","CountryCode":"PL","Name":"Krzywa","NameEN":"","NameDE":"","NameES":"","NameFR":"","NameIT":"","NameRU":""},{"Id":"110529306","CountryCode":"PL","Name":"Tadeusza Ko\u015Bciuszki","NameEN":"","NameDE":"","NameES":"","NameFR":"","NameIT":"","NameRU":""},{"Id":"33015826","CountryCode":"PL","Name":"Stanis\u0142awa Moniuszki","NameEN":"","NameDE":"","NameES":"","NameFR":"","NameIT":"","NameRU":""},{"Id":"23708858","CountryCode":"PL","Name":"Stanis\u0142awa Ligonia","NameEN":"","NameDE":"","NameES":"","NameFR":"","NameIT":"","NameRU":""},{"Id":"174745392","CountryCode":"PL","Name":"Plac J\u00F3zefa Lompy","NameEN":"","NameDE":"","NameES":"","NameFR":"","NameIT":"","NameRU":""},{"Id":"208428712","CountryCode":"PL","Name":"Weso\u0142a","NameEN":"","NameDE":"","NameES":"","NameFR":"","NameIT":"","NameRU":""},{"Id":"237125837","CountryCode":"PL","Name":"Franciszka My\u015Bliwca","NameEN":"","NameDE":"","NameES":"","NameFR":"","NameIT":"","NameRU":""},{"Id":"944001260","CountryCode":"PL","Name":"Ezechiela Orlika","NameEN":"","NameDE":"","NameES":"","NameFR":"","NameIT":"","NameRU":""},{"Id":"216382015","CountryCode":"PL","Name":"Wysocka","NameEN":"","NameDE":"","NameES":"","NameFR":"","NameIT":"","NameRU":""},{"Id":"230901012","CountryCode":"PL","Name":"Dolna Lipa","NameEN":"","NameDE":"","NameES":"","NameFR":"","NameIT":"","NameRU":""},{"Id":"216381968","CountryCode":"PL","Name":"Stara Poczta","NameEN":"","NameDE":"","NameES":"","NameFR":"","NameIT":"","NameRU":""},{"Id":"237112508","CountryCode":"PL","Name":"Przeskok","NameEN":"","NameDE":"","NameES":"","NameFR":"","NameIT":"","NameRU":""},{"Id":"230901484","CountryCode":"PL","Name":"Biadaczowa","NameEN":"","NameDE":"","NameES":"","NameFR":"","NameIT":"","NameRU":""},{"Id":"182374993","CountryCode":"PL","Name":"Poznowicka","NameEN":"","NameDE":"","NameES":"","NameFR":"","NameIT":"","NameRU":""},{"Id":"182230918","CountryCode":"PL","Name":"Floriana","NameEN":"","NameDE":"","NameES":"","NameFR":"","NameIT":"","NameRU":""},{"Id":"182034115","CountryCode":"PL","Name":"My\u015Bliwca","NameEN":"","NameDE":"","NameES":"","NameFR":"","NameIT":"","NameRU":""},{"Id":"170325308","CountryCode":"PL","Name":"Ksi\u0119dza Jana Dzier\u017Cona","NameEN":"","NameDE":"","NameES":"","NameFR":"","NameIT":"","NameRU":""},{"Id":"33014157","CountryCode":"PL","Name":"Poprzeczna","NameEN":"","NameDE":"","NameES":"","NameFR":"","NameIT":"","NameRU":""},{"Id":"170325328","CountryCode":"PL","Name":"Alberta Koszyka","NameEN":"","NameDE":"","NameES":"","NameFR":"","NameIT":"","NameRU":""},{"Id":"170325313","CountryCode":"PL","Name":"Wojciecha Korfantego","NameEN":"","NameDE":"","NameES":"","NameFR":"","NameIT":"","NameRU":""},{"Id":"170325341","CountryCode":"PL","Name":"Hrabi\u00F3w von Gaschin","NameEN":"","NameDE":"","NameES":"","NameFR":"","NameIT":"","NameRU":""},{"Id":"273785369","CountryCode":"PL","Name":"Por\u0119bska","NameEN":"","NameDE":"","NameES":"","NameFR":"","NameIT":"","NameRU":""},{"Id":"209362167","CountryCode":"PL","Name":"Plac Wolno\u015Bci","NameEN":"","NameDE":"","NameES":"","NameFR":"","NameIT":"","NameRU":""},{"Id":"150190746","CountryCode":"PL","Name":"Jaryszowska","NameEN":"","NameDE":"","NameES":"","NameFR":"","NameIT":"","NameRU":""},{"Id":"23672005","CountryCode":"PL","Name":"Boguszycka","NameEN":"","NameDE":"","NameES":"","NameFR":"","NameIT":"","NameRU":""},{"Id":"189529306","CountryCode":"PL","Name":"Grabina","NameEN":"","NameDE":"","NameES":"","NameFR":"","NameIT":"","NameRU":""},{"Id":"516449029","CountryCode":"PL","Name":"Suska","NameEN":"","NameDE":"","NameES":"","NameFR":"","NameIT":"","NameRU":""},{"Id":"516456727","CountryCode":"PL","Name":"Wolbromska","NameEN":"","NameDE":"","NameES":"","NameFR":"","NameIT":"","NameRU":""},{"Id":"237593209","CountryCode":"PL","Name":"Kar\u0142ubska","NameEN":"","NameDE":"","NameES":"","NameFR":"","NameIT":"","NameRU":""},{"Id":"150190703","CountryCode":"PL","Name":"Spokojna","NameEN":"","NameDE":"","NameES":"","NameFR":"","NameIT":"","NameRU":""},{"Id":"208197330","CountryCode":"PL","Name":"Ameryka\u0144ska","NameEN":"","NameDE":"","NameES":"","NameFR":"","NameIT":"","NameRU":""},{"Id":"574221609","CountryCode":"PL","Name":"Radosna","NameEN":"","NameDE":"","NameES":"","NameFR":"","NameIT":"","NameRU":""},{"Id":"35712840","CountryCode":"PL","Name":"Grabie","NameEN":"","NameDE":"","NameES":"","NameFR":"","NameIT":"","NameRU":""},{"Id":"516450945","CountryCode":"PL","Name":"Szlachecka","NameEN":"","NameDE":"","NameES":"","NameFR":"","NameIT":"","NameRU":""},{"Id":"516452649","CountryCode":"PL","Name":"Szwajcary","NameEN":"","NameDE":"","NameES":"","NameFR":"","NameIT":"","NameRU":""},{"Id":"516451244","CountryCode":"PL","Name":"Podg\u00F3rska","NameEN":"","NameDE":"","NameES":"","NameFR":"","NameIT":"","NameRU":""},{"Id":"611307575","CountryCode":"PL","Name":"S\u0142onecznikowa","NameEN":"","NameDE":"","NameES":"","NameFR":"","NameIT":"","NameRU":""},{"Id":"547222042","CountryCode":"PL","Name":"Hodowlana","NameEN":"","NameDE":"","NameES":"","NameFR":"","NameIT":"","NameRU":""},{"Id":"189505178","CountryCode":"PL","Name":"Laura","NameEN":"","NameDE":"","NameES":"","NameFR":"","NameIT":"","NameRU":""},{"Id":"112503237","CountryCode":"PL","Name":"Niemiecka","NameEN":"","NameDE":"","NameES":"","NameFR":"","NameIT":"","NameRU":""},{"Id":"112503256","CountryCode":"PL","Name":"Winnica","NameEN":"","NameDE":"","NameES":"","NameFR":"","NameIT":"","NameRU":""},{"Id":"271071847","CountryCode":"PL","Name":"Le\u015Bnicz\u00F3wka","NameEN":"","NameDE":"","NameES":"","NameFR":"","NameIT":"","NameRU":""},{"Id":"278723801","CountryCode":"PL","Name":"Che\u0142m","NameEN":"","NameDE":"","NameES":"","NameFR":"","NameIT":"","NameRU":""},{"Id":"275684466","CountryCode":"PL","Name":"Francuska","NameEN":"","NameDE":"","NameES":"","NameFR":"","NameIT":"","NameRU":""},{"Id":"688238159","CountryCode":"PL","Name":"Waltera Hengsta","NameEN":"","NameDE":"","NameES":"","NameFR":"","NameIT":"","NameRU":""},{"Id":"234543626","CountryCode":"PL","Name":"Irlandzka","NameEN":"","NameDE":"","NameES":"","NameFR":"","NameIT":"","NameRU":""},{"Id":"749257375","CountryCode":"PL","Name":"Gruszecka","NameEN":"","NameDE":"","NameES":"","NameFR":"","NameIT":"","NameRU":""},{"Id":"33021053","CountryCode":"PL","Name":"Ksi\u0119dza Ignacego Skorupki","NameEN":"","NameDE":"","NameES":"","NameFR":"","NameIT":"","NameRU":""},{"Id":"70862794","CountryCode":"PL","Name":"Transportowa","NameEN":"","NameDE":"","NameES":"","NameFR":"","NameIT":"","NameRU":""},{"Id":"387598044","CountryCode":"PL","Name":"\u015Awi\u0119toja\u0144ska","NameEN":"","NameDE":"","NameES":"","NameFR":"","NameIT":"","NameRU":""},{"Id":"112503254","CountryCode":"PL","Name":"Wjazdowa","NameEN":"","NameDE":"","NameES":"","NameFR":"","NameIT":"","NameRU":""},{"Id":"197644318","CountryCode":"PL","Name":"Promienna","NameEN":"","NameDE":"","NameES":"","NameFR":"","NameIT":"","NameRU":""},{"Id":"836008897","CountryCode":"PL","Name":"Kazimierza Odnowiciela","NameEN":"","NameDE":"","NameES":"","NameFR":"","NameIT":"","NameRU":""},{"Id":"33024990","CountryCode":"PL","Name":"Gajowa","NameEN":"","NameDE":"","NameES":"","NameFR":"","NameIT":"","NameRU":""},{"Id":"234562951","CountryCode":"PL","Name":"Zap\u0142otna","NameEN":"","NameDE":"","NameES":"","NameFR":"","NameIT":"","NameRU":""},{"Id":"923125009","CountryCode":"PL","Name":"Przyjazna","NameEN":"","NameDE":"","NameES":"","NameFR":"","NameIT":"","NameRU":""},{"Id":"174322057","CountryCode":"PL","Name":"Dunikowskiego","NameEN":"","NameDE":"","NameES":"","NameFR":"","NameIT":"","NameRU":""},{"Id":"196848956","CountryCode":"PL","Name":"Kazimierza Wielkiego","NameEN":"","NameDE":"","NameES":"","NameFR":"","NameIT":"","NameRU":""},{"Id":"236845127","CountryCode":"PL","Name":"Dzier\u017Conia","NameEN":"","NameDE":"","NameES":"","NameFR":"","NameIT":"","NameRU":""},{"Id":"962363416","CountryCode":"PL","Name":"Jerzego Klimasa","NameEN":"","NameDE":"","NameES":"","NameFR":"","NameIT":"","NameRU":""},{"Id":"259032714","CountryCode":"PL","Name":"Podle\u015Bna","NameEN":"","NameDE":"","NameES":"","NameFR":"","NameIT":"","NameRU":""},{"Id":"968537364","CountryCode":"PL","Name":"Odrow\u0105\u017C\u00F3w","NameEN":"","NameDE":"","NameES":"","NameFR":"","NameIT":"","NameRU":""},{"Id":"785723618","CountryCode":"PL","Name":"Czes\u0142awa Mi\u0142osza","NameEN":"","NameDE":"","NameES":"","NameFR":"","NameIT":"","NameRU":""},{"Id":"33026541","CountryCode":"PL","Name":"Bie\u0142awin","NameEN":"","NameDE":"","NameES":"","NameFR":"","NameIT":"","NameRU":""},{"Id":"990497554","CountryCode":"PL","Name":"Stefanii Wojtulanis","NameEN":"","NameDE":"","NameES":"","NameFR":"","NameIT":"","NameRU":""},{"Id":"997128721","CountryCode":"PL","Name":"Leopolda Staffa","NameEN":"","NameDE":"","NameES":"","NameFR":"","NameIT":"","NameRU":""},{"Id":"785723613","CountryCode":"PL","Name":"Bia\u0142owieska","NameEN":"","NameDE":"","NameES":"","NameFR":"","NameIT":"","NameRU":""},{"Id":"33021900","CountryCode":"PL","Name":"Mazurska","NameEN":"","NameDE":"","NameES":"","NameFR":"","NameIT":"","NameRU":""},{"Id":"33030287","CountryCode":"PL","Name":"Pomorska","NameEN":"","NameDE":"","NameES":"","NameFR":"","NameIT":"","NameRU":""},{"Id":"33012186","CountryCode":"PL","Name":"Mimozy","NameEN":"","NameDE":"","NameES":"","NameFR":"","NameIT":"","NameRU":""},{"Id":"33022576","CountryCode":"PL","Name":"Doktora Stefana \u017Barnowskiego","NameEN":"","NameDE":"","NameES":"","NameFR":"","NameIT":"","NameRU":""},{"Id":"377412618","CountryCode":"PL","Name":"Polska","NameEN":"","NameDE":"","NameES":"","NameFR":"","NameIT":"","NameRU":""},{"Id":"173446277","CountryCode":"PL","Name":"Euzebiusza Ferta","NameEN":"","NameDE":"","NameES":"","NameFR":"","NameIT":"","NameRU":""},{"Id":"759005043","CountryCode":"PL","Name":"Lawendowa","NameEN":"","NameDE":"","NameES":"","NameFR":"","NameIT":"","NameRU":""},{"Id":"33014469","CountryCode":"PL","Name":"Klonowa","NameEN":"","NameDE":"","NameES":"","NameFR":"","NameIT":"","NameRU":""},{"Id":"1284371993","CountryCode":"PL","Name":"Bruno Hampla","NameEN":"","NameDE":"","NameES":"","NameFR":"","NameIT":"","NameRU":""},{"Id":"750308654","CountryCode":"PL","Name":"Rodzinna","NameEN":"","NameDE":"","NameES":"","NameFR":"","NameIT":"","NameRU":""},{"Id":"1092577727","CountryCode":"PL","Name":"Kultury przestrzeni","NameEN":"","NameDE":"","NameES":"","NameFR":"","NameIT":"","NameRU":""}]}