{"CityId":"280833551","CitySearchName":"\u017Bywiec","Streets":[{"Id":"23987467","CountryCode":"PL","Name":"Weso\u0142a","NameEN":"","NameDE":"","NameES":"","NameFR":"","NameIT":"","NameRU":""},{"Id":"34918339","CountryCode":"PL","Name":"Krakowska","NameEN":"","NameDE":"","NameES":"","NameFR":"","NameIT":"","NameRU":""},{"Id":"26556979","CountryCode":"PL","Name":"Stefana \u017Beromskiego","NameEN":"","NameDE":"","NameES":"","NameFR":"","NameIT":"","NameRU":""},{"Id":"48002306","CountryCode":"PL","Name":"\u015Awi\u0119tokrzyska","NameEN":"","NameDE":"","NameES":"","NameFR":"","NameIT":"","NameRU":""},{"Id":"40969983","CountryCode":"PL","Name":"Andrzeja Komonieckiego","NameEN":"","NameDE":"","NameES":"","NameFR":"","NameIT":"","NameRU":""},{"Id":"26556978","CountryCode":"PL","Name":"Aleja Legion\u00F3w","NameEN":"","NameDE":"","NameES":"","NameFR":"","NameIT":"","NameRU":""},{"Id":"48002341","CountryCode":"PL","Name":"Zielona","NameEN":"","NameDE":"","NameES":"","NameFR":"","NameIT":"","NameRU":""},{"Id":"237422237","CountryCode":"PL","Name":"Rynek","NameEN":"","NameDE":"","NameES":"","NameFR":"","NameIT":"","NameRU":""},{"Id":"34918334","CountryCode":"PL","Name":"Zamkowa","NameEN":"","NameDE":"","NameES":"","NameFR":"","NameIT":"","NameRU":""},{"Id":"164668221","CountryCode":"PL","Name":"Stefanii Sempo\u0142owskiej","NameEN":"","NameDE":"","NameES":"","NameFR":"","NameIT":"","NameRU":""},{"Id":"48002326","CountryCode":"PL","Name":"Plac Mariacki","NameEN":"","NameDE":"","NameES":"","NameFR":"","NameIT":"","NameRU":""},{"Id":"48002327","CountryCode":"PL","Name":"Adama Mickiewicza","NameEN":"","NameDE":"","NameES":"","NameFR":"","NameIT":"","NameRU":""},{"Id":"31749315","CountryCode":"PL","Name":"Tadeusza Ko\u015Bciuszki","NameEN":"","NameDE":"","NameES":"","NameFR":"","NameIT":"","NameRU":""},{"Id":"238831713","CountryCode":"PL","Name":"Osiedle M\u0142odych","NameEN":"","NameDE":"","NameES":"","NameFR":"","NameIT":"","NameRU":""},{"Id":"34918336","CountryCode":"PL","Name":"Powsta\u0144c\u00F3w \u015Al\u0105skich","NameEN":"","NameDE":"","NameES":"","NameFR":"","NameIT":"","NameRU":""},{"Id":"34917763","CountryCode":"PL","Name":"Henryka Sienkiewicza","NameEN":"","NameDE":"","NameES":"","NameFR":"","NameIT":"","NameRU":""},{"Id":"242255066","CountryCode":"PL","Name":"Szkolna","NameEN":"","NameDE":"","NameES":"","NameFR":"","NameIT":"","NameRU":""},{"Id":"48002293","CountryCode":"PL","Name":"Juliusza S\u0142owackiego","NameEN":"","NameDE":"","NameES":"","NameFR":"","NameIT":"","NameRU":""},{"Id":"319410836","CountryCode":"PL","Name":"Handlowa","NameEN":"","NameDE":"","NameES":"","NameFR":"","NameIT":"","NameRU":""},{"Id":"78608635","CountryCode":"PL","Name":"Ignacego Jana Paderewskiego","NameEN":"","NameDE":"","NameES":"","NameFR":"","NameIT":"","NameRU":""},{"Id":"40969979","CountryCode":"PL","Name":"Aleja Wolno\u015Bci","NameEN":"","NameDE":"","NameES":"","NameFR":"","NameIT":"","NameRU":""},{"Id":"57934926","CountryCode":"PL","Name":"Moszczanicka","NameEN":"","NameDE":"","NameES":"","NameFR":"","NameIT":"","NameRU":""},{"Id":"243963711","CountryCode":"PL","Name":"Kamienna","NameEN":"","NameDE":"","NameES":"","NameFR":"","NameIT":"","NameRU":""},{"Id":"32265849","CountryCode":"PL","Name":"Armii Krajowej","NameEN":"","NameDE":"","NameES":"","NameFR":"","NameIT":"","NameRU":""},{"Id":"26767112","CountryCode":"PL","Name":"Dworcowa","NameEN":"","NameDE":"","NameES":"","NameFR":"","NameIT":"","NameRU":""},{"Id":"181065041","CountryCode":"PL","Name":"Ksi\u0119dza Stanis\u0142awa S\u0142onki","NameEN":"","NameDE":"","NameES":"","NameFR":"","NameIT":"","NameRU":""},{"Id":"180837425","CountryCode":"PL","Name":"Stolarska","NameEN":"","NameDE":"","NameES":"","NameFR":"","NameIT":"","NameRU":""},{"Id":"180837421","CountryCode":"PL","Name":"Fabryczna","NameEN":"","NameDE":"","NameES":"","NameFR":"","NameIT":"","NameRU":""},{"Id":"78608403","CountryCode":"PL","Name":"Objazdowa","NameEN":"","NameDE":"","NameES":"","NameFR":"","NameIT":"","NameRU":""},{"Id":"48002295","CountryCode":"PL","Name":"Aleja Marsza\u0142ka J\u00F3zefa Pi\u0142sudskiego","NameEN":"","NameDE":"","NameES":"","NameFR":"","NameIT":"","NameRU":""},{"Id":"48002352","CountryCode":"PL","Name":"Zygmunta Krasi\u0144skiego","NameEN":"","NameDE":"","NameES":"","NameFR":"","NameIT":"","NameRU":""},{"Id":"238829985","CountryCode":"PL","Name":"Kocurowska","NameEN":"","NameDE":"","NameES":"","NameFR":"","NameIT":"","NameRU":""},{"Id":"261223753","CountryCode":"PL","Name":"Osiedle 700-lecia","NameEN":"","NameDE":"","NameES":"","NameFR":"","NameIT":"","NameRU":""},{"Id":"254134335","CountryCode":"PL","Name":"Osiedle Pod Grap\u0105","NameEN":"","NameDE":"","NameES":"","NameFR":"","NameIT":"","NameRU":""},{"Id":"48002345","CountryCode":"PL","Name":"Komisji Edukacji Narodowej","NameEN":"","NameDE":"","NameES":"","NameFR":"","NameIT":"","NameRU":""},{"Id":"48002296","CountryCode":"PL","Name":"Folwark","NameEN":"","NameDE":"","NameES":"","NameFR":"","NameIT":"","NameRU":""},{"Id":"217351900","CountryCode":"PL","Name":"Jana","NameEN":"","NameDE":"","NameES":"","NameFR":"","NameIT":"","NameRU":""},{"Id":"311940012","CountryCode":"PL","Name":"Po\u0142udniowa","NameEN":"","NameDE":"","NameES":"","NameFR":"","NameIT":"","NameRU":""},{"Id":"227951709","CountryCode":"PL","Name":"G\u00F3ra Burga\u0142owska","NameEN":"","NameDE":"","NameES":"","NameFR":"","NameIT":"","NameRU":""},{"Id":"48002350","CountryCode":"PL","Name":"J\u00F3zefa Poniatowskiego","NameEN":"","NameDE":"","NameES":"","NameFR":"","NameIT":"","NameRU":""},{"Id":"227951768","CountryCode":"PL","Name":"\u015Ali\u017Cowy Potok","NameEN":"","NameDE":"","NameES":"","NameFR":"","NameIT":"","NameRU":""},{"Id":"48002301","CountryCode":"PL","Name":"\u0141\u0105czki","NameEN":"","NameDE":"","NameES":"","NameFR":"","NameIT":"","NameRU":""},{"Id":"48002319","CountryCode":"PL","Name":"Zacisze","NameEN":"","NameDE":"","NameES":"","NameFR":"","NameIT":"","NameRU":""},{"Id":"242255063","CountryCode":"PL","Name":"Jana Kazimierza","NameEN":"","NameDE":"","NameES":"","NameFR":"","NameIT":"","NameRU":""},{"Id":"48002311","CountryCode":"PL","Name":"R\u00F3\u017Cana","NameEN":"","NameDE":"","NameES":"","NameFR":"","NameIT":"","NameRU":""},{"Id":"48002310","CountryCode":"PL","Name":"Za Wod\u0105","NameEN":"","NameDE":"","NameES":"","NameFR":"","NameIT":"","NameRU":""},{"Id":"181065042","CountryCode":"PL","Name":"Kazimierza Tetmajera","NameEN":"","NameDE":"","NameES":"","NameFR":"","NameIT":"","NameRU":""},{"Id":"48002331","CountryCode":"PL","Name":"J\u00F3zefa Ignacego Kraszewskiego","NameEN":"","NameDE":"","NameES":"","NameFR":"","NameIT":"","NameRU":""},{"Id":"311031749","CountryCode":"PL","Name":"Jana III Sobieskiego","NameEN":"","NameDE":"","NameES":"","NameFR":"","NameIT":"","NameRU":""},{"Id":"48002302","CountryCode":"PL","Name":"Bracka","NameEN":"","NameDE":"","NameES":"","NameFR":"","NameIT":"","NameRU":""},{"Id":"48002323","CountryCode":"PL","Name":"Stefana Batorego","NameEN":"","NameDE":"","NameES":"","NameFR":"","NameIT":"","NameRU":""},{"Id":"48002324","CountryCode":"PL","Name":"3 Maja","NameEN":"","NameDE":"","NameES":"","NameFR":"","NameIT":"","NameRU":""},{"Id":"48002313","CountryCode":"PL","Name":"W\u0119glowa","NameEN":"","NameDE":"","NameES":"","NameFR":"","NameIT":"","NameRU":""},{"Id":"48002332","CountryCode":"PL","Name":"Piernikarska","NameEN":"","NameDE":"","NameES":"","NameFR":"","NameIT":"","NameRU":""},{"Id":"34918332","CountryCode":"PL","Name":"Jagiello\u0144ska","NameEN":"","NameDE":"","NameES":"","NameFR":"","NameIT":"","NameRU":""},{"Id":"48002325","CountryCode":"PL","Name":"Ma\u0142a","NameEN":"","NameDE":"","NameES":"","NameFR":"","NameIT":"","NameRU":""},{"Id":"34918335","CountryCode":"PL","Name":"Komorowskich","NameEN":"","NameDE":"","NameES":"","NameFR":"","NameIT":"","NameRU":""},{"Id":"26767110","CountryCode":"PL","Name":"Miko\u0142aja Kopernika","NameEN":"","NameDE":"","NameES":"","NameFR":"","NameIT":"","NameRU":""},{"Id":"78608426","CountryCode":"PL","Name":"Le\u015Bnianka","NameEN":"","NameDE":"","NameES":"","NameFR":"","NameIT":"","NameRU":""},{"Id":"48002340","CountryCode":"PL","Name":"Szewska","NameEN":"","NameDE":"","NameES":"","NameFR":"","NameIT":"","NameRU":""},{"Id":"172446687","CountryCode":"PL","Name":"Osiedle Parkowe","NameEN":"","NameDE":"","NameES":"","NameFR":"","NameIT":"","NameRU":""},{"Id":"48002292","CountryCode":"PL","Name":"Pod G\u00F3r\u0105","NameEN":"","NameDE":"","NameES":"","NameFR":"","NameIT":"","NameRU":""},{"Id":"40969975","CountryCode":"PL","Name":"Browarna","NameEN":"","NameDE":"","NameES":"","NameFR":"","NameIT":"","NameRU":""},{"Id":"48002291","CountryCode":"PL","Name":"Kr\u00F3tka","NameEN":"","NameDE":"","NameES":"","NameFR":"","NameIT":"","NameRU":""},{"Id":"48002343","CountryCode":"PL","Name":"M\u0142y\u0144ska","NameEN":"","NameDE":"","NameES":"","NameFR":"","NameIT":"","NameRU":""},{"Id":"174091640","CountryCode":"PL","Name":"Rzeczna","NameEN":"","NameDE":"","NameES":"","NameFR":"","NameIT":"","NameRU":""},{"Id":"181065017","CountryCode":"PL","Name":"Marii Konopnickiej","NameEN":"","NameDE":"","NameES":"","NameFR":"","NameIT":"","NameRU":""},{"Id":"309134629","CountryCode":"PL","Name":"W\u0105ska","NameEN":"","NameDE":"","NameES":"","NameFR":"","NameIT":"","NameRU":""},{"Id":"181065038","CountryCode":"PL","Name":"1 Maja","NameEN":"","NameDE":"","NameES":"","NameFR":"","NameIT":"","NameRU":""},{"Id":"34918337","CountryCode":"PL","Name":"S\u0142owicza","NameEN":"","NameDE":"","NameES":"","NameFR":"","NameIT":"","NameRU":""},{"Id":"48002354","CountryCode":"PL","Name":"PCK","NameEN":"","NameDE":"","NameES":"","NameFR":"","NameIT":"","NameRU":""},{"Id":"254316218","CountryCode":"PL","Name":"Turystyczna","NameEN":"","NameDE":"","NameES":"","NameFR":"","NameIT":"","NameRU":""},{"Id":"255241424","CountryCode":"PL","Name":"Prosta","NameEN":"","NameDE":"","NameES":"","NameFR":"","NameIT":"","NameRU":""},{"Id":"180837428","CountryCode":"PL","Name":"\u0141\u0105czna","NameEN":"","NameDE":"","NameES":"","NameFR":"","NameIT":"","NameRU":""},{"Id":"254134324","CountryCode":"PL","Name":"Wodna","NameEN":"","NameDE":"","NameES":"","NameFR":"","NameIT":"","NameRU":""},{"Id":"69976569","CountryCode":"PL","Name":"Grunwaldzka","NameEN":"","NameDE":"","NameES":"","NameFR":"","NameIT":"","NameRU":""},{"Id":"181065011","CountryCode":"PL","Name":"Futrzarska","NameEN":"","NameDE":"","NameES":"","NameFR":"","NameIT":"","NameRU":""},{"Id":"181065036","CountryCode":"PL","Name":"Sadowa","NameEN":"","NameDE":"","NameES":"","NameFR":"","NameIT":"","NameRU":""},{"Id":"181065033","CountryCode":"PL","Name":"Rze\u017Anicza","NameEN":"","NameDE":"","NameES":"","NameFR":"","NameIT":"","NameRU":""},{"Id":"181065043","CountryCode":"PL","Name":"Wa\u0142owa","NameEN":"","NameDE":"","NameES":"","NameFR":"","NameIT":"","NameRU":""},{"Id":"244238279","CountryCode":"PL","Name":"Aleja Jana Paw\u0142a II","NameEN":"","NameDE":"","NameES":"","NameFR":"","NameIT":"","NameRU":""},{"Id":"48002290","CountryCode":"PL","Name":"Wincentego Witosa","NameEN":"","NameDE":"","NameES":"","NameFR":"","NameIT":"","NameRU":""},{"Id":"48002317","CountryCode":"PL","Name":"Pi\u0119kna","NameEN":"","NameDE":"","NameES":"","NameFR":"","NameIT":"","NameRU":""},{"Id":"254316210","CountryCode":"PL","Name":"Piotra Skargi","NameEN":"","NameDE":"","NameES":"","NameFR":"","NameIT":"","NameRU":""},{"Id":"900612462","CountryCode":"PL","Name":"Stanis\u0142awa Wyspia\u0144skiego","NameEN":"","NameDE":"","NameES":"","NameFR":"","NameIT":"","NameRU":""},{"Id":"254316201","CountryCode":"PL","Name":"Ksi\u0119dza Zdzis\u0142awa Dzidka","NameEN":"","NameDE":"","NameES":"","NameFR":"","NameIT":"","NameRU":""},{"Id":"181065009","CountryCode":"PL","Name":"Bielska","NameEN":"","NameDE":"","NameES":"","NameFR":"","NameIT":"","NameRU":""},{"Id":"180837420","CountryCode":"PL","Name":"Biel\u00F3w","NameEN":"","NameDE":"","NameES":"","NameFR":"","NameIT":"","NameRU":""},{"Id":"48002316","CountryCode":"PL","Name":"Kolejowa","NameEN":"","NameDE":"","NameES":"","NameFR":"","NameIT":"","NameRU":""},{"Id":"229757596","CountryCode":"PL","Name":"Podlesie","NameEN":"","NameDE":"","NameES":"","NameFR":"","NameIT":"","NameRU":""},{"Id":"48002322","CountryCode":"PL","Name":"Ogrodowa","NameEN":"","NameDE":"","NameES":"","NameFR":"","NameIT":"","NameRU":""},{"Id":"234076055","CountryCode":"PL","Name":"Podwale","NameEN":"","NameDE":"","NameES":"","NameFR":"","NameIT":"","NameRU":""},{"Id":"78608461","CountryCode":"PL","Name":"Pilnikarska","NameEN":"","NameDE":"","NameES":"","NameFR":"","NameIT":"","NameRU":""},{"Id":"48002349","CountryCode":"PL","Name":"Habsburg\u00F3w","NameEN":"","NameDE":"","NameES":"","NameFR":"","NameIT":"","NameRU":""},{"Id":"227951710","CountryCode":"PL","Name":"Jana Karola Chodkiewicza","NameEN":"","NameDE":"","NameES":"","NameFR":"","NameIT":"","NameRU":""},{"Id":"227951706","CountryCode":"PL","Name":"Ernesta Malinowskiego","NameEN":"","NameDE":"","NameES":"","NameFR":"","NameIT":"","NameRU":""},{"Id":"227951725","CountryCode":"PL","Name":"Stanis\u0142awa \u017B\u00F3\u0142kiewskiego","NameEN":"","NameDE":"","NameES":"","NameFR":"","NameIT":"","NameRU":""},{"Id":"227951707","CountryCode":"PL","Name":"Krzysztofa Kamila Baczy\u0144skiego","NameEN":"","NameDE":"","NameES":"","NameFR":"","NameIT":"","NameRU":""},{"Id":"227951717","CountryCode":"PL","Name":"Marii D\u0105browskiej","NameEN":"","NameDE":"","NameES":"","NameFR":"","NameIT":"","NameRU":""},{"Id":"255523170","CountryCode":"PL","Name":"Nad Markiem","NameEN":"","NameDE":"","NameES":"","NameFR":"","NameIT":"","NameRU":""},{"Id":"180837423","CountryCode":"PL","Name":"Przemys\u0142owa","NameEN":"","NameDE":"","NameES":"","NameFR":"","NameIT":"","NameRU":""},{"Id":"48002307","CountryCode":"PL","Name":"Kabaty","NameEN":"","NameDE":"","NameES":"","NameFR":"","NameIT":"","NameRU":""},{"Id":"231817836","CountryCode":"PL","Name":"Bzowa","NameEN":"","NameDE":"","NameES":"","NameFR":"","NameIT":"","NameRU":""},{"Id":"231817849","CountryCode":"PL","Name":"Niezapominajki","NameEN":"","NameDE":"","NameES":"","NameFR":"","NameIT":"","NameRU":""},{"Id":"231817835","CountryCode":"PL","Name":"Bratkowa","NameEN":"","NameDE":"","NameES":"","NameFR":"","NameIT":"","NameRU":""},{"Id":"164646479","CountryCode":"PL","Name":"Suska","NameEN":"","NameDE":"","NameES":"","NameFR":"","NameIT":"","NameRU":""},{"Id":"308898643","CountryCode":"PL","Name":"Pierwiosnkowa","NameEN":"","NameDE":"","NameES":"","NameFR":"","NameIT":"","NameRU":""},{"Id":"302794525","CountryCode":"PL","Name":"Rychwa\u0142dzka","NameEN":"","NameDE":"","NameES":"","NameFR":"","NameIT":"","NameRU":""},{"Id":"255243594","CountryCode":"PL","Name":"Gajka","NameEN":"","NameDE":"","NameES":"","NameFR":"","NameIT":"","NameRU":""},{"Id":"255241449","CountryCode":"PL","Name":"Za \u0141ysk\u0105","NameEN":"","NameDE":"","NameES":"","NameFR":"","NameIT":"","NameRU":""},{"Id":"243855043","CountryCode":"PL","Name":"Habdas\u00F3wka","NameEN":"","NameDE":"","NameES":"","NameFR":"","NameIT":"","NameRU":""},{"Id":"243855044","CountryCode":"PL","Name":"Nadrzeczna","NameEN":"","NameDE":"","NameES":"","NameFR":"","NameIT":"","NameRU":""},{"Id":"254316203","CountryCode":"PL","Name":"Grobla","NameEN":"","NameDE":"","NameES":"","NameFR":"","NameIT":"","NameRU":""},{"Id":"243966952","CountryCode":"PL","Name":"Zgody","NameEN":"","NameDE":"","NameES":"","NameFR":"","NameIT":"","NameRU":""},{"Id":"1212549298","CountryCode":"PL","Name":"Spokojna","NameEN":"","NameDE":"","NameES":"","NameFR":"","NameIT":"","NameRU":""},{"Id":"181065052","CountryCode":"PL","Name":"Browar Kolonia","NameEN":"","NameDE":"","NameES":"","NameFR":"","NameIT":"","NameRU":""},{"Id":"181065012","CountryCode":"PL","Name":"Garbarska","NameEN":"","NameDE":"","NameES":"","NameFR":"","NameIT":"","NameRU":""},{"Id":"180837422","CountryCode":"PL","Name":"Joachima Lelewela","NameEN":"","NameDE":"","NameES":"","NameFR":"","NameIT":"","NameRU":""},{"Id":"181065031","CountryCode":"PL","Name":"Rolnicza","NameEN":"","NameDE":"","NameES":"","NameFR":"","NameIT":"","NameRU":""},{"Id":"181065040","CountryCode":"PL","Name":"S\u0142oneczna","NameEN":"","NameDE":"","NameES":"","NameFR":"","NameIT":"","NameRU":""},{"Id":"243963717","CountryCode":"PL","Name":"Okr\u0119\u017Cna","NameEN":"","NameDE":"","NameES":"","NameFR":"","NameIT":"","NameRU":""},{"Id":"180837426","CountryCode":"PL","Name":"Wyzwolenia","NameEN":"","NameDE":"","NameES":"","NameFR":"","NameIT":"","NameRU":""},{"Id":"179680751","CountryCode":"PL","Name":"Sporyska","NameEN":"","NameDE":"","NameES":"","NameFR":"","NameIT":"","NameRU":""},{"Id":"181065020","CountryCode":"PL","Name":"Ludna","NameEN":"","NameDE":"","NameES":"","NameFR":"","NameIT":"","NameRU":""},{"Id":"181065039","CountryCode":"PL","Name":"Sportowa","NameEN":"","NameDE":"","NameES":"","NameFR":"","NameIT":"","NameRU":""},{"Id":"181065027","CountryCode":"PL","Name":"Podtorze","NameEN":"","NameDE":"","NameES":"","NameFR":"","NameIT":"","NameRU":""},{"Id":"181065024","CountryCode":"PL","Name":"Nowa","NameEN":"","NameDE":"","NameES":"","NameFR":"","NameIT":"","NameRU":""},{"Id":"255523171","CountryCode":"PL","Name":"Irysowa","NameEN":"","NameDE":"","NameES":"","NameFR":"","NameIT":"","NameRU":""},{"Id":"255536096","CountryCode":"PL","Name":"Sezamowa","NameEN":"","NameDE":"","NameES":"","NameFR":"","NameIT":"","NameRU":""},{"Id":"109723170","CountryCode":"PL","Name":"Osiedle Kabaty","NameEN":"","NameDE":"","NameES":"","NameFR":"","NameIT":"","NameRU":""},{"Id":"255536097","CountryCode":"PL","Name":"Lawendowa","NameEN":"","NameDE":"","NameES":"","NameFR":"","NameIT":"","NameRU":""},{"Id":"255241425","CountryCode":"PL","Name":"Mi\u0142a","NameEN":"","NameDE":"","NameES":"","NameFR":"","NameIT":"","NameRU":""},{"Id":"32265857","CountryCode":"PL","Name":"Nimas\u00F3w","NameEN":"","NameDE":"","NameES":"","NameFR":"","NameIT":"","NameRU":""},{"Id":"181065029","CountryCode":"PL","Name":"P\u00F3\u0142kole","NameEN":"","NameDE":"","NameES":"","NameFR":"","NameIT":"","NameRU":""},{"Id":"227919343","CountryCode":"PL","Name":"Jod\u0142owa","NameEN":"","NameDE":"","NameES":"","NameFR":"","NameIT":"","NameRU":""},{"Id":"227919342","CountryCode":"PL","Name":"Makowa","NameEN":"","NameDE":"","NameES":"","NameFR":"","NameIT":"","NameRU":""},{"Id":"180837424","CountryCode":"PL","Name":"Stawowa","NameEN":"","NameDE":"","NameES":"","NameFR":"","NameIT":"","NameRU":""},{"Id":"231817848","CountryCode":"PL","Name":"Liliowa","NameEN":"","NameDE":"","NameES":"","NameFR":"","NameIT":"","NameRU":""},{"Id":"308770249","CountryCode":"PL","Name":"Beskidzka","NameEN":"","NameDE":"","NameES":"","NameFR":"","NameIT":"","NameRU":""},{"Id":"227919339","CountryCode":"PL","Name":"Pogodna","NameEN":"","NameDE":"","NameES":"","NameFR":"","NameIT":"","NameRU":""},{"Id":"308770255","CountryCode":"PL","Name":"Stroma","NameEN":"","NameDE":"","NameES":"","NameFR":"","NameIT":"","NameRU":""},{"Id":"172065935","CountryCode":"PL","Name":"Osiedle na Wzg\u00F3rzu","NameEN":"","NameDE":"","NameES":"","NameFR":"","NameIT":"","NameRU":""},{"Id":"171942367","CountryCode":"PL","Name":"\u015Awi\u0119tego Wita","NameEN":"","NameDE":"","NameES":"","NameFR":"","NameIT":"","NameRU":""},{"Id":"575687686","CountryCode":"PL","Name":"Gwiezdna","NameEN":"","NameDE":"","NameES":"","NameFR":"","NameIT":"","NameRU":""},{"Id":"231817884","CountryCode":"PL","Name":"Wschodnia","NameEN":"","NameDE":"","NameES":"","NameFR":"","NameIT":"","NameRU":""},{"Id":"231817860","CountryCode":"PL","Name":"Za G\u00F3r\u0105","NameEN":"","NameDE":"","NameES":"","NameFR":"","NameIT":"","NameRU":""},{"Id":"577463498","CountryCode":"PL","Name":"Pla\u017Cowa","NameEN":"","NameDE":"","NameES":"","NameFR":"","NameIT":"","NameRU":""},{"Id":"577463497","CountryCode":"PL","Name":"Dzia\u0142y Zadzielskie","NameEN":"","NameDE":"","NameES":"","NameFR":"","NameIT":"","NameRU":""},{"Id":"577463502","CountryCode":"PL","Name":"Rekreacyjna","NameEN":"","NameDE":"","NameES":"","NameFR":"","NameIT":"","NameRU":""},{"Id":"31749316","CountryCode":"PL","Name":"Kr\u00F3lowej Jadwigi","NameEN":"","NameDE":"","NameES":"","NameFR":"","NameIT":"","NameRU":""},{"Id":"172065942","CountryCode":"PL","Name":"Nad Witem","NameEN":"","NameDE":"","NameES":"","NameFR":"","NameIT":"","NameRU":""},{"Id":"231817857","CountryCode":"PL","Name":"Stokrotkowa","NameEN":"","NameDE":"","NameES":"","NameFR":"","NameIT":"","NameRU":""},{"Id":"231817850","CountryCode":"PL","Name":"Oczkowska","NameEN":"","NameDE":"","NameES":"","NameFR":"","NameIT":"","NameRU":""},{"Id":"231817858","CountryCode":"PL","Name":"Storczykowa","NameEN":"","NameDE":"","NameES":"","NameFR":"","NameIT":"","NameRU":""},{"Id":"308898645","CountryCode":"PL","Name":"Tulipanowa","NameEN":"","NameDE":"","NameES":"","NameFR":"","NameIT":"","NameRU":""},{"Id":"231817861","CountryCode":"PL","Name":"Wrzosowa","NameEN":"","NameDE":"","NameES":"","NameFR":"","NameIT":"","NameRU":""},{"Id":"231817900","CountryCode":"PL","Name":"\u017Bonkilowa","NameEN":"","NameDE":"","NameES":"","NameFR":"","NameIT":"","NameRU":""},{"Id":"308898644","CountryCode":"PL","Name":"Przebi\u015Bniegowa","NameEN":"","NameDE":"","NameES":"","NameFR":"","NameIT":"","NameRU":""},{"Id":"231817856","CountryCode":"PL","Name":"Sasankowa","NameEN":"","NameDE":"","NameES":"","NameFR":"","NameIT":"","NameRU":""},{"Id":"231817890","CountryCode":"PL","Name":"S\u0142onecznikowa","NameEN":"","NameDE":"","NameES":"","NameFR":"","NameIT":"","NameRU":""},{"Id":"1002763036","CountryCode":"PL","Name":"Konwaliowa","NameEN":"","NameDE":"","NameES":"","NameFR":"","NameIT":"","NameRU":""},{"Id":"231817843","CountryCode":"PL","Name":"Kalinowa","NameEN":"","NameDE":"","NameES":"","NameFR":"","NameIT":"","NameRU":""},{"Id":"308898642","CountryCode":"PL","Name":"Narcyzowa","NameEN":"","NameDE":"","NameES":"","NameFR":"","NameIT":"","NameRU":""},{"Id":"255538835","CountryCode":"PL","Name":"Podmiejska","NameEN":"","NameDE":"","NameES":"","NameFR":"","NameIT":"","NameRU":""},{"Id":"255536095","CountryCode":"PL","Name":"Skowronkowa","NameEN":"","NameDE":"","NameES":"","NameFR":"","NameIT":"","NameRU":""},{"Id":"255536093","CountryCode":"PL","Name":"Owocowa","NameEN":"","NameDE":"","NameES":"","NameFR":"","NameIT":"","NameRU":""},{"Id":"255536092","CountryCode":"PL","Name":"Sarni Stok","NameEN":"","NameDE":"","NameES":"","NameFR":"","NameIT":"","NameRU":""},{"Id":"575628082","CountryCode":"PL","Name":"Wietrzna","NameEN":"","NameDE":"","NameES":"","NameFR":"","NameIT":"","NameRU":""},{"Id":"255536090","CountryCode":"PL","Name":"Omast\u00F3wka","NameEN":"","NameDE":"","NameES":"","NameFR":"","NameIT":"","NameRU":""},{"Id":"255536091","CountryCode":"PL","Name":"Zaspowa","NameEN":"","NameDE":"","NameES":"","NameFR":"","NameIT":"","NameRU":""},{"Id":"240569653","CountryCode":"PL","Name":"W\u0142adys\u0142awa Warne\u0144czyka","NameEN":"","NameDE":"","NameES":"","NameFR":"","NameIT":"","NameRU":""},{"Id":"227951719","CountryCode":"PL","Name":"Mieszka I","NameEN":"","NameDE":"","NameES":"","NameFR":"","NameIT":"","NameRU":""},{"Id":"48002288","CountryCode":"PL","Name":"\u017Bywiecka","NameEN":"","NameDE":"","NameES":"","NameFR":"","NameIT":"","NameRU":""},{"Id":"181065013","CountryCode":"PL","Name":"Harenda","NameEN":"","NameDE":"","NameES":"","NameFR":"","NameIT":"","NameRU":""},{"Id":"181065975","CountryCode":"PL","Name":"Osiedle Zgoda","NameEN":"","NameDE":"","NameES":"","NameFR":"","NameIT":"","NameRU":""},{"Id":"181065014","CountryCode":"PL","Name":"Isep","NameEN":"","NameDE":"","NameES":"","NameFR":"","NameIT":"","NameRU":""},{"Id":"255241429","CountryCode":"PL","Name":"D\u0142uga","NameEN":"","NameDE":"","NameES":"","NameFR":"","NameIT":"","NameRU":""},{"Id":"255241428","CountryCode":"PL","Name":"Mochnackiego","NameEN":"","NameDE":"","NameES":"","NameFR":"","NameIT":"","NameRU":""},{"Id":"181065048","CountryCode":"PL","Name":"\u0141\u0119gowa","NameEN":"","NameDE":"","NameES":"","NameFR":"","NameIT":"","NameRU":""},{"Id":"181065016","CountryCode":"PL","Name":"Jana Kochanowskiego","NameEN":"","NameDE":"","NameES":"","NameFR":"","NameIT":"","NameRU":""},{"Id":"255241433","CountryCode":"PL","Name":"Jasna","NameEN":"","NameDE":"","NameES":"","NameFR":"","NameIT":"","NameRU":""},{"Id":"298005345","CountryCode":"PL","Name":"Ksi\u0119dza Stanis\u0142awa Stoja\u0142owskiego","NameEN":"","NameDE":"","NameES":"","NameFR":"","NameIT":"","NameRU":""},{"Id":"255534876","CountryCode":"PL","Name":"M\u0142yn","NameEN":"","NameDE":"","NameES":"","NameFR":"","NameIT":"","NameRU":""},{"Id":"78608658","CountryCode":"PL","Name":"Stanis\u0142awa Sosabowskiego","NameEN":"","NameDE":"","NameES":"","NameFR":"","NameIT":"","NameRU":""},{"Id":"110801101","CountryCode":"PL","Name":"Tadeusza Bora-Komorowskiego","NameEN":"","NameDE":"","NameES":"","NameFR":"","NameIT":"","NameRU":""},{"Id":"78608606","CountryCode":"PL","Name":"Strzelc\u00F3w Karpackich","NameEN":"","NameDE":"","NameES":"","NameFR":"","NameIT":"","NameRU":""},{"Id":"78608462","CountryCode":"PL","Name":"W\u0142adys\u0142awa Andersa","NameEN":"","NameDE":"","NameES":"","NameFR":"","NameIT":"","NameRU":""},{"Id":"110801542","CountryCode":"PL","Name":"Jana Sowi\u0144skiego","NameEN":"","NameDE":"","NameES":"","NameFR":"","NameIT":"","NameRU":""},{"Id":"172962692","CountryCode":"PL","Name":"Orl\u0105t Lwowskich","NameEN":"","NameDE":"","NameES":"","NameFR":"","NameIT":"","NameRU":""},{"Id":"255534877","CountryCode":"PL","Name":"Franciszka Kleeberga","NameEN":"","NameDE":"","NameES":"","NameFR":"","NameIT":"","NameRU":""},{"Id":"227970689","CountryCode":"PL","Name":"Stanis\u0142awa Maczka","NameEN":"","NameDE":"","NameES":"","NameFR":"","NameIT":"","NameRU":""},{"Id":"110782307","CountryCode":"PL","Name":"Bluszczowa","NameEN":"","NameDE":"","NameES":"","NameFR":"","NameIT":"","NameRU":""},{"Id":"231817837","CountryCode":"PL","Name":"B\u0142awatkowa","NameEN":"","NameDE":"","NameES":"","NameFR":"","NameIT":"","NameRU":""},{"Id":"110801103","CountryCode":"PL","Name":"Azaliowa","NameEN":"","NameDE":"","NameES":"","NameFR":"","NameIT":"","NameRU":""},{"Id":"110801097","CountryCode":"PL","Name":"Nad Jeziorem","NameEN":"","NameDE":"","NameES":"","NameFR":"","NameIT":"","NameRU":""},{"Id":"110801098","CountryCode":"PL","Name":"Astr\u00F3w","NameEN":"","NameDE":"","NameES":"","NameFR":"","NameIT":"","NameRU":""},{"Id":"110782339","CountryCode":"PL","Name":"Cyprysowa","NameEN":"","NameDE":"","NameES":"","NameFR":"","NameIT":"","NameRU":""},{"Id":"231817838","CountryCode":"PL","Name":"Chabrowa","NameEN":"","NameDE":"","NameES":"","NameFR":"","NameIT":"","NameRU":""},{"Id":"227951712","CountryCode":"PL","Name":"Konstantego Ildefonsa Ga\u0142czy\u0144skiego","NameEN":"","NameDE":"","NameES":"","NameFR":"","NameIT":"","NameRU":""},{"Id":"227951722","CountryCode":"PL","Name":"Przyjaci\u00F3\u0142","NameEN":"","NameDE":"","NameES":"","NameFR":"","NameIT":"","NameRU":""},{"Id":"227951726","CountryCode":"PL","Name":"Stefana Czarnieckiego","NameEN":"","NameDE":"","NameES":"","NameFR":"","NameIT":"","NameRU":""},{"Id":"227951711","CountryCode":"PL","Name":"Jana Zamoyskiego","NameEN":"","NameDE":"","NameES":"","NameFR":"","NameIT":"","NameRU":""},{"Id":"227951727","CountryCode":"PL","Name":"Stra\u017Cacka","NameEN":"","NameDE":"","NameES":"","NameFR":"","NameIT":"","NameRU":""},{"Id":"255534880","CountryCode":"PL","Name":"Nad \u0141\u0119kawk\u0105","NameEN":"","NameDE":"","NameES":"","NameFR":"","NameIT":"","NameRU":""},{"Id":"42770860","CountryCode":"PL","Name":"\u015Alemie\u0144ska","NameEN":"","NameDE":"","NameES":"","NameFR":"","NameIT":"","NameRU":""},{"Id":"238830295","CountryCode":"PL","Name":"Nad Dworem","NameEN":"","NameDE":"","NameES":"","NameFR":"","NameIT":"","NameRU":""},{"Id":"227951714","CountryCode":"PL","Name":"Cypriana Kamila Norwida","NameEN":"","NameDE":"","NameES":"","NameFR":"","NameIT":"","NameRU":""},{"Id":"309177753","CountryCode":"PL","Name":"Leopolda Staffa","NameEN":"","NameDE":"","NameES":"","NameFR":"","NameIT":"","NameRU":""},{"Id":"227951716","CountryCode":"PL","Name":"Lucjana Rydla","NameEN":"","NameDE":"","NameES":"","NameFR":"","NameIT":"","NameRU":""},{"Id":"828891674","CountryCode":"PL","Name":"Hetmana Jana Tarnowskiego","NameEN":"","NameDE":"","NameES":"","NameFR":"","NameIT":"","NameRU":""},{"Id":"227951729","CountryCode":"PL","Name":"Boles\u0142awa Krzywoustego","NameEN":"","NameDE":"","NameES":"","NameFR":"","NameIT":"","NameRU":""},{"Id":"309177752","CountryCode":"PL","Name":"Gabrieli Zapolskiej","NameEN":"","NameDE":"","NameES":"","NameFR":"","NameIT":"","NameRU":""},{"Id":"309177754","CountryCode":"PL","Name":"W\u0142adys\u0142awa \u0141okietka","NameEN":"","NameDE":"","NameES":"","NameFR":"","NameIT":"","NameRU":""},{"Id":"227951747","CountryCode":"PL","Name":"Jana Kasprowicza","NameEN":"","NameDE":"","NameES":"","NameFR":"","NameIT":"","NameRU":""},{"Id":"227951720","CountryCode":"PL","Name":"Piastowska","NameEN":"","NameDE":"","NameES":"","NameFR":"","NameIT":"","NameRU":""},{"Id":"227951704","CountryCode":"PL","Name":"Aleksandra Fredry","NameEN":"","NameDE":"","NameES":"","NameFR":"","NameIT":"","NameRU":""},{"Id":"227951728","CountryCode":"PL","Name":"Zawiszy Czarnego","NameEN":"","NameDE":"","NameES":"","NameFR":"","NameIT":"","NameRU":""},{"Id":"227951703","CountryCode":"PL","Name":"Adama Asnyka","NameEN":"","NameDE":"","NameES":"","NameFR":"","NameIT":"","NameRU":""},{"Id":"181065049","CountryCode":"PL","Name":"\u017Beglarska","NameEN":"","NameDE":"","NameES":"","NameFR":"","NameIT":"","NameRU":""},{"Id":"179680752","CountryCode":"PL","Name":"Grojec","NameEN":"","NameDE":"","NameES":"","NameFR":"","NameIT":"","NameRU":""},{"Id":"227919347","CountryCode":"PL","Name":"Wi\u015Bniowa","NameEN":"","NameDE":"","NameES":"","NameFR":"","NameIT":"","NameRU":""},{"Id":"308770256","CountryCode":"PL","Name":"Wierzbowa","NameEN":"","NameDE":"","NameES":"","NameFR":"","NameIT":"","NameRU":""},{"Id":"227919346","CountryCode":"PL","Name":"Kasztanowa","NameEN":"","NameDE":"","NameES":"","NameFR":"","NameIT":"","NameRU":""},{"Id":"227919341","CountryCode":"PL","Name":"Akacjowa","NameEN":"","NameDE":"","NameES":"","NameFR":"","NameIT":"","NameRU":""},{"Id":"227919350","CountryCode":"PL","Name":"Topolowa","NameEN":"","NameDE":"","NameES":"","NameFR":"","NameIT":"","NameRU":""},{"Id":"227919340","CountryCode":"PL","Name":"Jaworowa","NameEN":"","NameDE":"","NameES":"","NameFR":"","NameIT":"","NameRU":""},{"Id":"255536089","CountryCode":"PL","Name":"Malownicza","NameEN":"","NameDE":"","NameES":"","NameFR":"","NameIT":"","NameRU":""},{"Id":"181065037","CountryCode":"PL","Name":"Marii Sk\u0142odowskiej-Curie","NameEN":"","NameDE":"","NameES":"","NameFR":"","NameIT":"","NameRU":""},{"Id":"255241446","CountryCode":"PL","Name":"Pod \u0141ysk\u0105","NameEN":"","NameDE":"","NameES":"","NameFR":"","NameIT":"","NameRU":""},{"Id":"164675380","CountryCode":"PL","Name":"Klonowa","NameEN":"","NameDE":"","NameES":"","NameFR":"","NameIT":"","NameRU":""},{"Id":"181065015","CountryCode":"PL","Name":"Jana Kili\u0144skiego","NameEN":"","NameDE":"","NameES":"","NameFR":"","NameIT":"","NameRU":""},{"Id":"181065030","CountryCode":"PL","Name":"Miko\u0142aja Reja","NameEN":"","NameDE":"","NameES":"","NameFR":"","NameIT":"","NameRU":""},{"Id":"255241431","CountryCode":"PL","Name":"Mleczarska","NameEN":"","NameDE":"","NameES":"","NameFR":"","NameIT":"","NameRU":""},{"Id":"243855046","CountryCode":"PL","Name":"Pola Lisickich","NameEN":"","NameDE":"","NameES":"","NameFR":"","NameIT":"","NameRU":""},{"Id":"217336403","CountryCode":"PL","Name":"Partyzant\u00F3w","NameEN":"","NameDE":"","NameES":"","NameFR":"","NameIT":"","NameRU":""},{"Id":"254316204","CountryCode":"PL","Name":"Jana Matejki","NameEN":"","NameDE":"","NameES":"","NameFR":"","NameIT":"","NameRU":""},{"Id":"243963739","CountryCode":"PL","Name":"\u0141agodna","NameEN":"","NameDE":"","NameES":"","NameFR":"","NameIT":"","NameRU":""},{"Id":"243963716","CountryCode":"PL","Name":"Okopowa","NameEN":"","NameDE":"","NameES":"","NameFR":"","NameIT":"","NameRU":""},{"Id":"243963740","CountryCode":"PL","Name":"\u0141\u0105kowa","NameEN":"","NameDE":"","NameES":"","NameFR":"","NameIT":"","NameRU":""},{"Id":"497451995","CountryCode":"PL","Name":"Graniczna","NameEN":"","NameDE":"","NameES":"","NameFR":"","NameIT":"","NameRU":""},{"Id":"321873760","CountryCode":"PL","Name":"Nad Stawem","NameEN":"","NameDE":"","NameES":"","NameFR":"","NameIT":"","NameRU":""},{"Id":"243855045","CountryCode":"PL","Name":"Osiedle Miko\u0142aja Kopernika","NameEN":"","NameDE":"","NameES":"","NameFR":"","NameIT":"","NameRU":""},{"Id":"254316211","CountryCode":"PL","Name":"W\u0142adys\u0142awa Stanis\u0142awa Reymonta","NameEN":"","NameDE":"","NameES":"","NameFR":"","NameIT":"","NameRU":""},{"Id":"254316206","CountryCode":"PL","Name":"Osiedle Reymonta","NameEN":"","NameDE":"","NameES":"","NameFR":"","NameIT":"","NameRU":""},{"Id":"183772082","CountryCode":"PL","Name":"\u017Bwirowa","NameEN":"","NameDE":"","NameES":"","NameFR":"","NameIT":"","NameRU":""},{"Id":"243963726","CountryCode":"PL","Name":"Stawy","NameEN":"","NameDE":"","NameES":"","NameFR":"","NameIT":"","NameRU":""},{"Id":"243963715","CountryCode":"PL","Name":"Nad Koszaraw\u0105","NameEN":"","NameDE":"","NameES":"","NameFR":"","NameIT":"","NameRU":""},{"Id":"243963714","CountryCode":"PL","Name":"K\u0105towa","NameEN":"","NameDE":"","NameES":"","NameFR":"","NameIT":"","NameRU":""},{"Id":"243963712","CountryCode":"PL","Name":"Kolista","NameEN":"","NameDE":"","NameES":"","NameFR":"","NameIT":"","NameRU":""},{"Id":"243963718","CountryCode":"PL","Name":"Osiedlowa","NameEN":"","NameDE":"","NameES":"","NameFR":"","NameIT":"","NameRU":""},{"Id":"243963729","CountryCode":"PL","Name":"Wiklinowa","NameEN":"","NameDE":"","NameES":"","NameFR":"","NameIT":"","NameRU":""},{"Id":"243963722","CountryCode":"PL","Name":"Potoczna","NameEN":"","NameDE":"","NameES":"","NameFR":"","NameIT":"","NameRU":""},{"Id":"217399675","CountryCode":"PL","Name":"Kwiatowa","NameEN":"","NameDE":"","NameES":"","NameFR":"","NameIT":"","NameRU":""},{"Id":"243963708","CountryCode":"PL","Name":"G\u00F3rska","NameEN":"","NameDE":"","NameES":"","NameFR":"","NameIT":"","NameRU":""},{"Id":"243963723","CountryCode":"PL","Name":"Pszczelna","NameEN":"","NameDE":"","NameES":"","NameFR":"","NameIT":"","NameRU":""},{"Id":"243963720","CountryCode":"PL","Name":"Podg\u00F3rska","NameEN":"","NameDE":"","NameES":"","NameFR":"","NameIT":"","NameRU":""},{"Id":"243963705","CountryCode":"PL","Name":"Boczna","NameEN":"","NameDE":"","NameES":"","NameFR":"","NameIT":"","NameRU":""},{"Id":"243963730","CountryCode":"PL","Name":"Wsp\u00F3lna","NameEN":"","NameDE":"","NameES":"","NameFR":"","NameIT":"","NameRU":""},{"Id":"243963721","CountryCode":"PL","Name":"Poprzeczna","NameEN":"","NameDE":"","NameES":"","NameFR":"","NameIT":"","NameRU":""},{"Id":"243963728","CountryCode":"PL","Name":"Wapienna","NameEN":"","NameDE":"","NameES":"","NameFR":"","NameIT":"","NameRU":""},{"Id":"308848976","CountryCode":"PL","Name":"Magnoliowa","NameEN":"","NameDE":"","NameES":"","NameFR":"","NameIT":"","NameRU":""},{"Id":"243963707","CountryCode":"PL","Name":"Grabowa","NameEN":"","NameDE":"","NameES":"","NameFR":"","NameIT":"","NameRU":""},{"Id":"243963727","CountryCode":"PL","Name":"Stokowa","NameEN":"","NameDE":"","NameES":"","NameFR":"","NameIT":"","NameRU":""},{"Id":"243963724","CountryCode":"PL","Name":"Spadzista","NameEN":"","NameDE":"","NameES":"","NameFR":"","NameIT":"","NameRU":""},{"Id":"254316200","CountryCode":"PL","Name":"Brzozowa","NameEN":"","NameDE":"","NameES":"","NameFR":"","NameIT":"","NameRU":""},{"Id":"217337262","CountryCode":"PL","Name":"Grapa","NameEN":"","NameDE":"","NameES":"","NameFR":"","NameIT":"","NameRU":""},{"Id":"255243592","CountryCode":"PL","Name":"Cicha","NameEN":"","NameDE":"","NameES":"","NameFR":"","NameIT":"","NameRU":""},{"Id":"255243591","CountryCode":"PL","Name":"Sosnowa","NameEN":"","NameDE":"","NameES":"","NameFR":"","NameIT":"","NameRU":""},{"Id":"297070218","CountryCode":"PL","Name":"\u015Awi\u0119tego Huberta","NameEN":"","NameDE":"","NameES":"","NameFR":"","NameIT":"","NameRU":""},{"Id":"255243593","CountryCode":"PL","Name":"Wierchy","NameEN":"","NameDE":"","NameES":"","NameFR":"","NameIT":"","NameRU":""},{"Id":"255243583","CountryCode":"PL","Name":"Cisowa","NameEN":"","NameDE":"","NameES":"","NameFR":"","NameIT":"","NameRU":""},{"Id":"217336406","CountryCode":"PL","Name":"Wichrowa","NameEN":"","NameDE":"","NameES":"","NameFR":"","NameIT":"","NameRU":""},{"Id":"255243590","CountryCode":"PL","Name":"Modrzewiowa","NameEN":"","NameDE":"","NameES":"","NameFR":"","NameIT":"","NameRU":""},{"Id":"255243589","CountryCode":"PL","Name":"Do Kopca","NameEN":"","NameDE":"","NameES":"","NameFR":"","NameIT":"","NameRU":""},{"Id":"576877848","CountryCode":"PL","Name":"Feliksa Kazimierza Potockiego","NameEN":"","NameDE":"","NameES":"","NameFR":"","NameIT":"","NameRU":""},{"Id":"181065028","CountryCode":"PL","Name":"Polna","NameEN":"","NameDE":"","NameES":"","NameFR":"","NameIT":"","NameRU":""},{"Id":"181065026","CountryCode":"PL","Name":"Piaskowa","NameEN":"","NameDE":"","NameES":"","NameFR":"","NameIT":"","NameRU":""},{"Id":"181065044","CountryCode":"PL","Name":"Wczasowa","NameEN":"","NameDE":"","NameES":"","NameFR":"","NameIT":"","NameRU":""},{"Id":"255241426","CountryCode":"PL","Name":"Micha\u0142a","NameEN":"","NameDE":"","NameES":"","NameFR":"","NameIT":"","NameRU":""},{"Id":"181065025","CountryCode":"PL","Name":"Pawlusie","NameEN":"","NameDE":"","NameES":"","NameFR":"","NameIT":"","NameRU":""},{"Id":"591363795","CountryCode":"PL","Name":"Wypoczynkowa","NameEN":"","NameDE":"","NameES":"","NameFR":"","NameIT":"","NameRU":""},{"Id":"722937530","CountryCode":"PL","Name":"Widokowa","NameEN":"","NameDE":"","NameES":"","NameFR":"","NameIT":"","NameRU":""},{"Id":"231817839","CountryCode":"PL","Name":"Chmielna","NameEN":"","NameDE":"","NameES":"","NameFR":"","NameIT":"","NameRU":""},{"Id":"255241432","CountryCode":"PL","Name":"Zab\u0142ocka","NameEN":"","NameDE":"","NameES":"","NameFR":"","NameIT":"","NameRU":""},{"Id":"181065018","CountryCode":"PL","Name":"Krzywa","NameEN":"","NameDE":"","NameES":"","NameFR":"","NameIT":"","NameRU":""},{"Id":"227951708","CountryCode":"PL","Name":"Granitowa","NameEN":"","NameDE":"","NameES":"","NameFR":"","NameIT":"","NameRU":""},{"Id":"255241443","CountryCode":"PL","Name":"Ja\u015Bminowa","NameEN":"","NameDE":"","NameES":"","NameFR":"","NameIT":"","NameRU":""},{"Id":"227951748","CountryCode":"PL","Name":"D\u0119bowa","NameEN":"","NameDE":"","NameES":"","NameFR":"","NameIT":"","NameRU":""},{"Id":"227951721","CountryCode":"PL","Name":"Pleba\u0144ska","NameEN":"","NameDE":"","NameES":"","NameFR":"","NameIT":"","NameRU":""},{"Id":"255241448","CountryCode":"PL","Name":"Pod Szko\u0142\u0105","NameEN":"","NameDE":"","NameES":"","NameFR":"","NameIT":"","NameRU":""},{"Id":"255243588","CountryCode":"PL","Name":"Orzechowa","NameEN":"","NameDE":"","NameES":"","NameFR":"","NameIT":"","NameRU":""},{"Id":"255243585","CountryCode":"PL","Name":"\u015Awierkowa","NameEN":"","NameDE":"","NameES":"","NameFR":"","NameIT":"","NameRU":""},{"Id":"255241444","CountryCode":"PL","Name":"Na Oklu","NameEN":"","NameDE":"","NameES":"","NameFR":"","NameIT":"","NameRU":""},{"Id":"255241445","CountryCode":"PL","Name":"Wiosenna","NameEN":"","NameDE":"","NameES":"","NameFR":"","NameIT":"","NameRU":""},{"Id":"254316213","CountryCode":"PL","Name":"Spacerowa","NameEN":"","NameDE":"","NameES":"","NameFR":"","NameIT":"","NameRU":""},{"Id":"254316209","CountryCode":"PL","Name":"Pierwog\u00F3ra","NameEN":"","NameDE":"","NameES":"","NameFR":"","NameIT":"","NameRU":""},{"Id":"227951705","CountryCode":"PL","Name":"Bohater\u00F3w Wrze\u015Bnia","NameEN":"","NameDE":"","NameES":"","NameFR":"","NameIT":"","NameRU":""},{"Id":"309177751","CountryCode":"PL","Name":"Boles\u0142awa Chrobrego","NameEN":"","NameDE":"","NameES":"","NameFR":"","NameIT":"","NameRU":""},{"Id":"227951733","CountryCode":"PL","Name":"Kazimierza Wielkiego","NameEN":"","NameDE":"","NameES":"","NameFR":"","NameIT":"","NameRU":""},{"Id":"78608653","CountryCode":"PL","Name":"Niwy","NameEN":"","NameDE":"","NameES":"","NameFR":"","NameIT":"","NameRU":""},{"Id":"231817841","CountryCode":"PL","Name":"Fio\u0142kowa","NameEN":"","NameDE":"","NameES":"","NameFR":"","NameIT":"","NameRU":""},{"Id":"231817842","CountryCode":"PL","Name":"G\u0142ogowa","NameEN":"","NameDE":"","NameES":"","NameFR":"","NameIT":"","NameRU":""},{"Id":"231817863","CountryCode":"PL","Name":"Mieczykowa","NameEN":"","NameDE":"","NameES":"","NameFR":"","NameIT":"","NameRU":""},{"Id":"231817847","CountryCode":"PL","Name":"Krokusowa","NameEN":"","NameDE":"","NameES":"","NameFR":"","NameIT":"","NameRU":""},{"Id":"828891678","CountryCode":"PL","Name":"Pod Jemio\u0142\u0105","NameEN":"","NameDE":"","NameES":"","NameFR":"","NameIT":"","NameRU":""},{"Id":"110801099","CountryCode":"PL","Name":"Stefana Grota Roweckiego","NameEN":"","NameDE":"","NameES":"","NameFR":"","NameIT":"","NameRU":""},{"Id":"984643152","CountryCode":"PL","Name":"Na Stoku","NameEN":"","NameDE":"","NameES":"","NameFR":"","NameIT":"","NameRU":""},{"Id":"237756972","CountryCode":"PL","Name":"Wakacyjna","NameEN":"","NameDE":"","NameES":"","NameFR":"","NameIT":"","NameRU":""},{"Id":"586102041","CountryCode":"PL","Name":"Tartaczna","NameEN":"","NameDE":"","NameES":"","NameFR":"","NameIT":"","NameRU":""},{"Id":"437480794","CountryCode":"PL","Name":"Rozwojowa","NameEN":"","NameDE":"","NameES":"","NameFR":"","NameIT":"","NameRU":""},{"Id":"568742058","CountryCode":"PL","Name":"Pod Lasem","NameEN":"","NameDE":"","NameES":"","NameFR":"","NameIT":"","NameRU":""},{"Id":"1163610507","CountryCode":"PL","Name":"Bukowa","NameEN":"","NameDE":"","NameES":"","NameFR":"","NameIT":"","NameRU":""}]}